Workbook

Sheet Summary 
A1: Project: | C1: ='Landscape R01'!D4 -> BELMORE RESIDENCES 305 Plot No. 6110305, Bukadra, Dubai, United Arab Emirates @Ras Al Khor | Q1: ='Landscape R01'!BK4 -> 46160
A2: Project Code: | C2: BELMORE RESIDENCES 305 | P2: Ref: | Q2: ='Landscape R01'!AZ4 &" - "&'Landscape R01'!BL4 -> CS/HO/PROC/P1026/CIV/26/12 - REV-0
A3: Client Name: | C3: M/s Ellington Properties Developments LLC
A4: Consultant: | C4: Kling Consult GMBH - Dubai
A5: Package Name: | C5: ='Landscape R01'!E2 -> COMPARISON STATEMENT FOR LANDSCAPING WORKS (SUPPLY & INSTALLATION)
A6: Bid Summary
A8: Sl No. | B8: Description | C8: Vendor Name | D8: Amount | J8: Payment Terms | N8: Securities | P8: Technical Compliance (Yes/No) | Q8: Remarks
D9: Rev 00 | E9: Rev 01 | F9: Rev 02 | G9: Rev 03 | H9: Rev 04 | I9: Final Offer | J9: Advance | K9: MOS | L9: Progress | M9: Retention | N9: Advance Guarantee / Cheque | O9: Performance Bond / Cheque
A10: 1 | B10: Lowest Vendor | C10: ='Landscape R01'!AF5 -> Green dunes | D10: ='Landscape R01'!AH130 -> 2272085.6 | E10: ='Landscape R01'!AJ130 -> 0 | I10: =D10 -> 2272085.6 | J10: 0.1 | K10: 0.5 | L10: 0.4 | M10: 0.1 | N10: SC | O10: 10% SC | P10: ='Landscape R01'!AF145 -> 0 | Q10: ='Landscape R01'!AI9 -> 0 | S10: =$D$26 -> 2189273.1 | T10: =IF(H10=0,G10,IF(G10=0,F10,IF(E10=0,D10,H10))) -> 0
A11: 2 | B11: 2nd Lowest | C11: ='Landscape R01'!Q5 -> Premier Irrigation & Landscaping L.L.C | D11: ='Landscape R01'!R130 -> 2379630.3 | E11: ='Landscape R01'!T130 -> 0 | I11: =D11 -> 2379630.3 | J11: 0.1 | L11: 0.9 | M11: 0.1 | N11: SC | O11: 10% SC | P11: ='Landscape R01'!Q145 -> 0 | Q11: ='Landscape R01'!S9 -> 0 | S11: =$D$26 -> 2189273.1
A12: 3 | B12: 3rd Lowest | C12: ='Landscape R01'!U5 -> Planta Lanndscaping & Irrigation L.L.C | D12: ='Landscape R01'!W130 -> 2816733 | E12: ='Landscape R01'!Y130 -> 0 | F12: ='Landscape R01'!AA130 -> 0 | G12: ='Landscape R01'!AC130 -> 0 | H12: ='Landscape R01'!AE130 -> 0 | I12: =D12 -> 2816733 | P12: ='Landscape R01'!U145 -> 0 | Q12: ='Landscape R01'!AD9 -> 0 | S12: =$D$26 -> 2189273.1
A13: 4 | B13: 4th Lowest | C13: ='Landscape R01'!H5 -> KTC INTERNATIONAL LANDSCAPING LLC | D13: ='Landscape R01'!J130 -> 3866696 | E13: ='Landscape R01'!L130 -> 0 | F13: ='Landscape R01'!P130 -> 0 | G13: ='Landscape R01'!N130 -> 0 | H13: =IF(H13=0,G13,IF(G13=0,IF(E13=0,D13,H13))) -> 0 | I13: =D13 -> 3866696 | K13: 0.5 | L13: 0.5 | M13: 0.1 | N13: NA | O13: 10%SC | P13: 20 Years - 359,228.02 25 years - 395,150.82 | Q13: ='Landscape R01'!O9 -> 0 | S13: =$D$26 -> 2189273.1
A14: 5 | B14: 5th Lowest | C14: ='Landscape R01'!AK5 -> 0 | D14: ='Landscape R01'!AL130 -> 0 | E14: ='Landscape R01'!AN130 -> 0 | F14: ='Landscape R01'!AP130 -> 0 | G14: ='Landscape R01'!AT130 -> 0 | H14: ='Landscape R01'!AR130 -> 0 | I14: ='Landscape R01'!AT130 -> 0 | P14: 20 Years - 456.979.71 25 years - 677,066.21 | Q14: ='Landscape R01'!AS9 -> 0 | S14: =$D$26 -> 2189273.1
A15: 6 | B15: 6th Lowest | C15: ='Landscape R01'!AU5 -> 0 | D15: ='Landscape R01'!AV130 -> 0 | E15: ='Landscape R01'!AX130 -> 0 | F15: ='Landscape R01'!AZ130 -> 0 | I15: =E15 -> 0 | J15: 0.1 | L15: 0.9 | M15: 0.1 | N15: BG | O15: 10% BG | P15: 20 Years - 464.231.34 25 years - 616,235.84 | Q15: ='Landscape R01'!AY9 -> 0 | S15: =$D$26 -> 2189273.1
A16: 7 | B16: 7th Lowest | C16: ='Landscape R01'!BA5 -> 0 | D16: ='Landscape R01'!BB130 -> 0 | E16: ='Landscape R01'!BD130 -> 0 | F16: ='Landscape R01'!BF130 -> 0 | I16: =F16 -> 0 | J16: 0.1 | K16: 0.4 | L16: 0.5 | M16: 0.1 | N16: SC | O16: 10% sc | P16: ='Landscape R01'!BA145 -> 0 | Q16: ='Landscape R01'!BE9 -> 0 | S16: =$D$26 -> 2189273.1
A17: 8 | B17: 8th Lowest | C17: ='Landscape R01'!BG5 -> 0 | D17: ='Landscape R01'!BH130 -> 0 | E17: ='Landscape R01'!BJ130 -> 0 | F17: ='Landscape R01'!BL130 -> 0 | I17: =F17 -> 0 | P17: ='Landscape R01'!BG145 -> 0 | Q17: ='Landscape R01'!BK9 -> 0 | S17: =$D$26 -> 2189273.1
A18: 7 | B18: 7th Lowest | C18: =[2]BidTab2!B13 -> 0 | I18: =VLOOKUP(C18,[2]BidTab2!B13:L21,5,FALSE) -> 0 | P18: =RIGHT([2]BidTab2!A10,16)
A19: 8 | B19: 8th Lowest | C19: =[2]BidTab2!B14 -> 0 | I19: =VLOOKUP(C19,[2]BidTab2!B14:L22,5,FALSE) -> 0 | P19: =RIGHT([2]BidTab2!A8,16)
A20: 9 | B20: 9th Lowest | C20: =[2]BidTab2!B15 -> 0 | I20: =VLOOKUP(C20,[2]BidTab2!B15:L23,5,FALSE) -> 0 | P20: =RIGHT([2]BidTab2!A9,16)
N21: Refer Bid Tab for details
B22: Recommended Vendor: | D22: =C10 -> Green dunes
B23: Back Up Vendor:
D25: Budget | E25: Selling
A26: Allowance | D26: ='Landscape R01'!G130 -> 2189273.1
A27: Order Value | D27: =I10 -> 2272085.6
A28: Profit/(Loss) | D28: =D26-D27 -> -82812.456 | E28: =E26-E27 -> 0
A30: NOTES | C30: Specified Material : | D30: ='Landscape R01'!U132 -> 0
C31: Warranty as per specs | D31: Warranty Substructure(20 years and extended warranty 25 years)

Sheet Landscape R01
E2: COMPARISON STATEMENT FOR LANDSCAPING WORKS (SUPPLY & INSTALLATION)
C4: Project Name: | D4: BELMORE RESIDENCES 305 Plot No. 6110305, Bukadra, Dubai, United Arab Emirates @Ras Al Khor | AY4: DOC Ref: | AZ4: CS/HO/PROC/P1026/CIV/26/12 | BJ4: DATE | BK4: 46160 | BL4: REV-0
B5: Sno | C5: Description | D5: Unit | H5: KTC INTERNATIONAL LANDSCAPING LLC | Q5: Premier Irrigation & Landscaping L.L.C | U5: Planta Lanndscaping & Irrigation L.L.C | AF5: Green dunes
E6: Quantity | F6: BCC Rate | G6: BCC Budget | H6: Naseek Erikunnan (971-5811 98257) naseek.erikunnan@ktcco.net | Q6: 971 55 995 0883 | U6: 971 55 842 7100 | AF6: Suhesh 971 52 123 5179
H7: KTCL/EQ25/255/R04 | Q7: KTCL/EQ25/263/R01 | U7: PLA/QTN/1025/1603_R02 | AF7: GD060/QTN/2026/0060
H8: 46161 | Q8: 46162 | U8: 46167 | AF8: 46179
H9: Remeasureable | Q9: Remeasureable | U9: Lumpsum | AF9: Lumpsum
H11: R0 Price | I11: Qty | J11: R0 Amount | K11: R1 Price | L11: R1 Amount | M11: R1 Price | N11: R1 Amount | O11: R1 Price | P11: R1 Amount | Q11: R0 Price | R11: R0 Amount | S11: R1 Price | T11: R1 Amount | U11: R0 Price | W11: R0 Amount | X11: R1 Price | Y11: R1 Amount | Z11: R2 Price | AA11: R2 Amount | AB11: R2 Price | AC11: R2 Amount | AD11: R2 Price | AE11: R2 Amount | AF11: R0 Price | AH11: R0 Amount | AI11: R1 Price | AJ11: R1 Amount | AK11: R0 Price | AL11: R0 Amount | AM11: R1 Price | AN11: R1 Amount | AO11: R2 Price | AP11: R2 Amount | AQ11: R3 Price | AR11: R3 Amount | AS11: R3 Price | AT11: R3 Amount | AU11: R0 Price | AV11: R0 Amount | AW11: R1 Price | AX11: R1 Amount | AY11: R1 Price | AZ11: R1 Amount | BA11: R0 Price | BB11: R0 Amount | BC11: R1 Price | BD11: R1 Amount | BE11: R2 Price | BF11: R2 Amount | BG11: R0 Price | BH11: R0 Amount | BI11: R1 Price | BJ11: R1 Amount | BK11: R2 Price | BL11: R2 Amount
C12: HARDSCAPE | BK12: unbonded
B13: =IF(ISBLANK($E13)," ",IF(AND(COUNTA(E$8:$E13)+64>72,COUNTA(E$8:$E13)+64<78),CHAR(COUNTA(E$8:$E13)+65),IF(COUNTA(E$8:$E13)+64>77,CHAR(COUNTA(E$8:$E13)+66),CHAR(COUNTA(E$8:$E13)+64)))) | C13: EXTERNAL WORKS
B14: =IF(ISBLANK($E14)," ",IF(AND(COUNTA(E$8:$E14)+64>72,COUNTA(E$8:$E14)+64<78),CHAR(COUNTA(E$8:$E14)+65),IF(COUNTA(E$8:$E14)+64>77,CHAR(COUNTA(E$8:$E14)+66),CHAR(COUNTA(E$8:$E14)+64)))) | C14: The Contractor is referred to the specifications and drawings for the details related to the works under this division and he is to include for complying with all the requirements contained therein, whether or not they are specifically mentioned within the Item.
B15: =IF(ISBLANK($E15)," ",IF(AND(COUNTA(E$8:$E15)+64>72,COUNTA(E$8:$E15)+64<78),CHAR(COUNTA(E$8:$E15)+65),IF(COUNTA(E$8:$E15)+64>77,CHAR(COUNTA(E$8:$E15)+66),CHAR(COUNTA(E$8:$E15)+64)))) | C15: External Floor Finishes
B16: =IF(ISBLANK($E16)," ",IF(AND(COUNTA(E$8:$E16)+64>72,COUNTA(E$8:$E16)+64<78),CHAR(COUNTA(E$8:$E16)+65),IF(COUNTA(E$8:$E16)+64>77,CHAR(COUNTA(E$8:$E16)+66),CHAR(COUNTA(E$8:$E16)+64)))) | C16: HARDSCAPE
C17: Supply and installation of hardscape including all necessary excavation and filling as required, sub base, screed, bedding materials, support, adhesives,grouts, spacers, trims, dividing strips (where applicable) and fixing accessories ..etc, all in accordance with Drawings, Specifications and to the Engineer's approval
B18: =IF(ISBLANK($E18)," ",IF(AND(COUNTA(E$8:$E18)+64>72,COUNTA(E$8:$E18)+64<78),CHAR(COUNTA(E$8:$E18)+65),IF(COUNTA(E$8:$E18)+64>77,CHAR(COUNTA(E$8:$E18)+66),CHAR(COUNTA(E$8:$E18)+64)))) -> A | C18: PA-01A - Concrete pavers 600x600x80mm | D18: m2 | E18: 5 | F18: 217.8 | G18: 1607.364 | H18: 534 | I18: 5 | J18: =H18*$I18 -> 2670 | L18: =K18*$E18 -> 0 | N18: =M18*$E18 -> 0 | P18: =O18*$E18 -> 0 | Q18: 280 | R18: =Q18*$E18 -> 1400 | T18: =S18*$E18 -> 0 | U18: 274 | V18: 177 | W18: =V18*U18 -> 48498 | Y18: =X18*$E18 -> 0 | AA18: =Z18*$E18 -> 0 | AC18: =AB18*$E18 -> 0 | AE18: =AD18*$E18 -> 0 | AF18: 226 | AG18: 178 | AH18: =AF18*$AG18 -> 40228 | AJ18: =AI18*$E18 -> 0 | AL18: =AK18*$E18 -> 0 | AN18: =AM18*$E18 -> 0 | AP18: =AO18*$E18 -> 0 | AR18: =AQ18*$E18 -> 0 | AT18: =AS18*$E18 -> 0 | AV18: =AU18*$E18 -> 0 | AX18: =AW18*$E18 -> 0 | AZ18: =AY18*$E18 -> 0 | BB18: =BA18*$E18 -> 0 | BD18: =BC18*$E18 -> 0 | BF18: =BE18*$E18 -> 0 | BH18: =BG18*$E18 -> 0 | BJ18: =BI18*$E18 -> 0 | BL18: =BK18*$E18 -> 0
B19: =IF(ISBLANK($E19)," ",IF(AND(COUNTA(E$8:$E19)+64>72,COUNTA(E$8:$E19)+64<78),CHAR(COUNTA(E$8:$E19)+65),IF(COUNTA(E$8:$E19)+64>77,CHAR(COUNTA(E$8:$E19)+66),CHAR(COUNTA(E$8:$E19)+64)))) -> B | C19: PA-01B - Concrete pavers 300x300x80mm | D19: m2 | E19: 2 | F19: 217.8 | G19: 1960.2 | H19: 534 | I19: 2 | J19: =H19*$I19 -> 1068 | L19: =K19*$E19 -> 0 | N19: =M19*$E19 -> 0 | P19: =O19*$E19 -> 0 | Q19: 245 | R19: =Q19*$E19 -> 490 | T19: =S19*$E19 -> 0 | U19: 274 | V19: 9 | W19: =V19*U19 -> 2466 | Y19: =X19*$E19 -> 0 | AA19: =Z19*$E19 -> 0 | AC19: =AB19*$E19 -> 0 | AE19: =AD19*$E19 -> 0 | AF19: 226 | AG19: 2 | AH19: =AF19*$AG19 -> 452 | AJ19: =AI19*$E19 -> 0 | AL19: =AK19*$E19 -> 0 | AN19: =AM19*$E19 -> 0 | AP19: =AO19*$E19 -> 0 | AR19: =AQ19*$E19 -> 0 | AT19: =AS19*$E19 -> 0 | AV19: =AU19*$E19 -> 0 | AX19: =AW19*$E19 -> 0 | AZ19: =AY19*$E19 -> 0 | BB19: =BA19*$E19 -> 0 | BD19: =BC19*$E19 -> 0 | BF19: =BE19*$E19 -> 0 | BH19: =BG19*$E19 -> 0 | BJ19: =BI19*$E19 -> 0 | BL19: =BK19*$E19 -> 0
B20: =IF(ISBLANK($E20)," ",IF(AND(COUNTA(E$8:$E20)+64>72,COUNTA(E$8:$E20)+64<78),CHAR(COUNTA(E$8:$E20)+65),IF(COUNTA(E$8:$E20)+64>77,CHAR(COUNTA(E$8:$E20)+66),CHAR(COUNTA(E$8:$E20)+64)))) -> C | C20: PA-01C - Concrete pavers 300x300x80mm | D20: m2 | E20: 7 | F20: 217.8 | G20: 3702.6 | H20: 534 | I20: 7 | J20: =H20*$I20 -> 3738 | L20: =K20*$E20 -> 0 | N20: =M20*$E20 -> 0 | P20: =O20*$E20 -> 0 | Q20: 245 | R20: =Q20*$E20 -> 1715 | T20: =S20*$E20 -> 0 | U20: 274 | V20: 17 | W20: =V20*U20 -> 4658 | Y20: =X20*$E20 -> 0 | AA20: =Z20*$E20 -> 0 | AC20: =AB20*$E20 -> 0 | AE20: =AD20*$E20 -> 0 | AF20: 226 | AG20: 7 | AH20: =AF20*$AG20 -> 1582 | AJ20: =AI20*$E20 -> 0 | AL20: =AK20*$E20 -> 0 | AN20: =AM20*$E20 -> 0 | AP20: =AO20*$E20 -> 0 | AR20: =AQ20*$E20 -> 0 | AT20: =AS20*$E20 -> 0 | AV20: =AU20*$E20 -> 0 | AX20: =AW20*$E20 -> 0 | AZ20: =AY20*$E20 -> 0 | BB20: =BA20*$E20 -> 0 | BD20: =BC20*$E20 -> 0 | BF20: =BE20*$E20 -> 0 | BH20: =BG20*$E20 -> 0 | BJ20: =BI20*$E20 -> 0 | BL20: =BK20*$E20 -> 0
B21: =IF(ISBLANK($E21)," ",IF(AND(COUNTA(E$8:$E21)+64>72,COUNTA(E$8:$E21)+64<78),CHAR(COUNTA(E$8:$E21)+65),IF(COUNTA(E$8:$E21)+64>77,CHAR(COUNTA(E$8:$E21)+66),CHAR(COUNTA(E$8:$E21)+64)))) -> D | C21: PA-02A - Porcelain tile 600x1200x10mm | D21: m2 | E21: 343 | F21: 233.1 | G21: 79953.3 | H21: 613 | I21: 343 | J21: =H21*$I21 -> 210259 | L21: =K21*$E21 -> 0 | N21: =M21*$E21 -> 0 | P21: =O21*$E21 -> 0 | Q21: 380 | R21: =Q21*$E21 -> 130340 | T21: =S21*$E21 -> 0 | U21: 294 | V21: 360 | W21: =V21*U21 -> 105840 | Y21: =X21*$E21 -> 0 | AA21: =Z21*$E21 -> 0 | AC21: =AB21*$E21 -> 0 | AE21: =AD21*$E21 -> 0 | AF21: 446 | AG21: 343 | AH21: =AF21*$AG21 -> 152978 | AJ21: =AI21*$E21 -> 0 | AL21: =AK21*$E21 -> 0 | AN21: =AM21*$E21 -> 0 | AP21: =AO21*$E21 -> 0 | AR21: =AQ21*$E21 -> 0 | AT21: =AS21*$E21 -> 0 | AV21: =AU21*$E21 -> 0 | AX21: =AW21*$E21 -> 0 | AZ21: =AY21*$E21 -> 0 | BB21: =BA21*$E21 -> 0 | BD21: =BC21*$E21 -> 0 | BF21: =BE21*$E21 -> 0 | BH21: =BG21*$E21 -> 0 | BJ21: =BI21*$E21 -> 0 | BL21: =BK21*$E21 -> 0
B22: =IF(ISBLANK($E22)," ",IF(AND(COUNTA(E$8:$E22)+64>72,COUNTA(E$8:$E22)+64<78),CHAR(COUNTA(E$8:$E22)+65),IF(COUNTA(E$8:$E22)+64>77,CHAR(COUNTA(E$8:$E22)+66),CHAR(COUNTA(E$8:$E22)+64)))) -> E | C22: PA-02B - Pool Porcelain tile 600x300x10mm (L05 - Adults and Kids pool) | D22: m2 | E22: 426 | F22: 65.7 | G22: 27988.2 | H22: 604 | I22: 426 | J22: =H22*$I22 -> 257304 | L22: =K22*$E22 -> 0 | N22: =M22*$E22 -> 0 | P22: =O22*$E22 -> 0 | Q22: 380 | R22: =Q22*$E22 -> 161880 | T22: =S22*$E22 -> 0 | V22: 426 | W22: =V22*U22 -> 0 | Y22: =X22*$E22 -> 0 | AA22: =Z22*$E22 -> 0 | AC22: =AB22*$E22 -> 0 | AE22: =AD22*$E22 -> 0 | AG22: 426 | AH22: =AF22*$AG22 -> 0 | AJ22: =AI22*$E22 -> 0 | AL22: =AK22*$E22 -> 0 | AN22: =AM22*$E22 -> 0 | AP22: =AO22*$E22 -> 0 | AR22: =AQ22*$E22 -> 0 | AT22: =AS22*$E22 -> 0 | AV22: =AU22*$E22 -> 0 | AX22: =AW22*$E22 -> 0 | AZ22: =AY22*$E22 -> 0 | BB22: =BA22*$E22 -> 0 | BD22: =BC22*$E22 -> 0 | BF22: =BE22*$E22 -> 0 | BH22: =BG22*$E22 -> 0 | BJ22: =BI22*$E22 -> 0 | BL22: =BK22*$E22 -> 0
B23: =IF(ISBLANK($E23)," ",IF(AND(COUNTA(E$8:$E23)+64>72,COUNTA(E$8:$E23)+64<78),CHAR(COUNTA(E$8:$E23)+65),IF(COUNTA(E$8:$E23)+64>77,CHAR(COUNTA(E$8:$E23)+66),CHAR(COUNTA(E$8:$E23)+64)))) -> F | C23: PA-02C - Porcelain tile 600x1200x9mm (L05 - Paving) | D23: m2 | E23: 454 | F23: 233.1 | G23: 110955.6 | H23: 656 | I23: 454 | J23: =H23*$I23 -> 297824 | L23: =K23*$E23 -> 0 | N23: =M23*$E23 -> 0 | P23: =O23*$E23 -> 0 | Q23: 380 | R23: =Q23*$E23 -> 172520 | T23: =S23*$E23 -> 0 | U23: 294 | V23: 476 | W23: =V23*U23 -> 139944 | Y23: =X23*$E23 -> 0 | AA23: =Z23*$E23 -> 0 | AC23: =AB23*$E23 -> 0 | AE23: =AD23*$E23 -> 0 | AF23: 466 | AG23: 454 | AH23: =AF23*$AG23 -> 211564 | AJ23: =AI23*$E23 -> 0 | AL23: =AK23*$E23 -> 0 | AN23: =AM23*$E23 -> 0 | AP23: =AO23*$E23 -> 0 | AR23: =AQ23*$E23 -> 0 | AT23: =AS23*$E23 -> 0 | AV23: =AU23*$E23 -> 0 | AX23: =AW23*$E23 -> 0 | AZ23: =AY23*$E23 -> 0 | BB23: =BA23*$E23 -> 0 | BD23: =BC23*$E23 -> 0 | BF23: =BE23*$E23 -> 0 | BH23: =BG23*$E23 -> 0 | BJ23: =BI23*$E23 -> 0 | BL23: =BK23*$E23 -> 0
B24: =IF(ISBLANK($E24)," ",IF(AND(COUNTA(E$8:$E24)+64>72,COUNTA(E$8:$E24)+64<78),CHAR(COUNTA(E$8:$E24)+65),IF(COUNTA(E$8:$E24)+64>77,CHAR(COUNTA(E$8:$E24)+66),CHAR(COUNTA(E$8:$E24)+64)))) -> G | C24: PA-02D - Porcelain tile 600x600x10mm (L05 - Seating pods paving and BBQ counter cladding) | D24: m2 | E24: 20 | F24: 233.1 | G24: 4662 | H24: 656 | I24: 20 | J24: =H24*$I24 -> 13120 | L24: =K24*$E24 -> 0 | N24: =M24*$E24 -> 0 | P24: =O24*$E24 -> 0 | Q24: 380 | R24: =Q24*$E24 -> 7600 | T24: =S24*$E24 -> 0 | U24: 294 | V24: 20 | W24: =V24*U24 -> 5880 | Y24: =X24*$E24 -> 0 | AA24: =Z24*$E24 -> 0 | AC24: =AB24*$E24 -> 0 | AE24: =AD24*$E24 -> 0 | AF24: 362 | AG24: 20 | AH24: =AF24*$AG24 -> 7240 | AJ24: =AI24*$E24 -> 0 | AL24: =AK24*$E24 -> 0 | AN24: =AM24*$E24 -> 0 | AP24: =AO24*$E24 -> 0 | AR24: =AQ24*$E24 -> 0 | AT24: =AS24*$E24 -> 0 | AV24: =AU24*$E24 -> 0 | AX24: =AW24*$E24 -> 0 | AZ24: =AY24*$E24 -> 0 | BB24: =BA24*$E24 -> 0 | BD24: =BC24*$E24 -> 0 | BF24: =BE24*$E24 -> 0 | BH24: =BG24*$E24 -> 0 | BJ24: =BI24*$E24 -> 0 | BL24: =BK24*$E24 -> 0
B25: =IF(ISBLANK($E25)," ",IF(AND(COUNTA(E$8:$E25)+64>72,COUNTA(E$8:$E25)+64<78),CHAR(COUNTA(E$8:$E25)+65),IF(COUNTA(E$8:$E25)+64>77,CHAR(COUNTA(E$8:$E25)+66),CHAR(COUNTA(E$8:$E25)+64)))) -> H | C25: PA-02E - Natural stone coping 600x300x30mm (L05 - Pool Edge Coping) | D25: m2 | E25: 17 | F25: 435.6 | G25: 7405.2 | H25: 1002 | I25: 17 | J25: =H25*$I25 -> 17034 | L25: =K25*$E25 -> 0 | N25: =M25*$E25 -> 0 | P25: =O25*$E25 -> 0 | Q25: 620 | R25: =Q25*$E25 -> 10540 | T25: =S25*$E25 -> 0 | U25: 658 | V25: 17 | W25: =V25*U25 -> 11186 | Y25: =X25*$E25 -> 0 | AA25: =Z25*$E25 -> 0 | AC25: =AB25*$E25 -> 0 | AE25: =AD25*$E25 -> 0 | AH25: =AF25*$AG25 -> 0 | AJ25: =AI25*$E25 -> 0 | AL25: =AK25*$E25 -> 0 | AN25: =AM25*$E25 -> 0 | AP25: =AO25*$E25 -> 0 | AR25: =AQ25*$E25 -> 0 | AT25: =AS25*$E25 -> 0 | AV25: =AU25*$E25 -> 0 | AX25: =AW25*$E25 -> 0 | AZ25: =AY25*$E25 -> 0 | BB25: =BA25*$E25 -> 0 | BD25: =BC25*$E25 -> 0 | BF25: =BE25*$E25 -> 0 | BH25: =BG25*$E25 -> 0 | BJ25: =BI25*$E25 -> 0 | BL25: =BK25*$E25 -> 0
B26: =IF(ISBLANK($E26)," ",IF(AND(COUNTA(E$8:$E26)+64>72,COUNTA(E$8:$E26)+64<78),CHAR(COUNTA(E$8:$E26)+65),IF(COUNTA(E$8:$E26)+64>77,CHAR(COUNTA(E$8:$E26)+66),CHAR(COUNTA(E$8:$E26)+64)))) -> J | C26: PA-02F - Porcelain grating tile 600x300x20mm (L05 - BMU mound path along the kids play area ) | D26: m2 | E26: 15 | F26: 288 | G26: 4320 | H26: 890 | I26: 15 | J26: =H26*$I26 -> 13350 | L26: =K26*$E26 -> 0 | N26: =M26*$E26 -> 0 | P26: =O26*$E26 -> 0 | Q26: 425 | R26: =Q26*$E26 -> 6375 | T26: =S26*$E26 -> 0 | U26: 411 | V26: 15 | W26: =V26*U26 -> 6165 | Y26: =X26*$E26 -> 0 | AA26: =Z26*$E26 -> 0 | AC26: =AB26*$E26 -> 0 | AE26: =AD26*$E26 -> 0 | AF26: 656 | AG26: 15 | AH26: =AF26*$AG26 -> 9840 | AJ26: =AI26*$E26 -> 0 | AL26: =AK26*$E26 -> 0 | AN26: =AM26*$E26 -> 0 | AP26: =AO26*$E26 -> 0 | AR26: =AQ26*$E26 -> 0 | AT26: =AS26*$E26 -> 0 | AV26: =AU26*$E26 -> 0 | AX26: =AW26*$E26 -> 0 | AZ26: =AY26*$E26 -> 0 | BB26: =BA26*$E26 -> 0 | BD26: =BC26*$E26 -> 0 | BF26: =BE26*$E26 -> 0 | BH26: =BG26*$E26 -> 0 | BJ26: =BI26*$E26 -> 0 | BL26: =BK26*$E26 -> 0
B27: =IF(ISBLANK($E27)," ",IF(AND(COUNTA(E$8:$E27)+64>72,COUNTA(E$8:$E27)+64<78),CHAR(COUNTA(E$8:$E27)+65),IF(COUNTA(E$8:$E27)+64>77,CHAR(COUNTA(E$8:$E27)+66),CHAR(COUNTA(E$8:$E27)+64)))) -> K | C27: PA-02G - Porcelain tile 365x1200x20mm ( L05 - Pool and paving steps tread) | D27: m2 | E27: 15 | F27: 288 | G27: 4320 | H27: 890 | I27: 15 | J27: =H27*$I27 -> 13350 | L27: =K27*$E27 -> 0 | N27: =M27*$E27 -> 0 | P27: =O27*$E27 -> 0 | Q27: 410 | R27: =Q27*$E27 -> 6150 | T27: =S27*$E27 -> 0 | U27: 363 | V27: 15 | W27: =V27*U27 -> 5445 | Y27: =X27*$E27 -> 0 | AA27: =Z27*$E27 -> 0 | AC27: =AB27*$E27 -> 0 | AE27: =AD27*$E27 -> 0 | AF27: 572 | AG27: 15 | AH27: =AF27*$AG27 -> 8580 | AJ27: =AI27*$E27 -> 0 | AL27: =AK27*$E27 -> 0 | AN27: =AM27*$E27 -> 0 | AP27: =AO27*$E27 -> 0 | AR27: =AQ27*$E27 -> 0 | AT27: =AS27*$E27 -> 0 | AV27: =AU27*$E27 -> 0 | AX27: =AW27*$E27 -> 0 | AZ27: =AY27*$E27 -> 0 | BB27: =BA27*$E27 -> 0 | BD27: =BC27*$E27 -> 0 | BF27: =BE27*$E27 -> 0 | BH27: =BG27*$E27 -> 0 | BJ27: =BI27*$E27 -> 0 | BL27: =BK27*$E27 -> 0
B28: =IF(ISBLANK($E28)," ",IF(AND(COUNTA(E$8:$E28)+64>72,COUNTA(E$8:$E28)+64<78),CHAR(COUNTA(E$8:$E28)+65),IF(COUNTA(E$8:$E28)+64>77,CHAR(COUNTA(E$8:$E28)+66),CHAR(COUNTA(E$8:$E28)+64)))) -> L | C28: PA-02H - Porcelain tile 300x1200x20mm (L05 - Pool steps tread) | D28: m2 | E28: 35.5 | F28: 313.2 | G28: 11275.2 | H28: 570 | I28: 36 | J28: =H28*$I28 -> 20520 | L28: =K28*$E28 -> 0 | N28: =M28*$E28 -> 0 | P28: =O28*$E28 -> 0 | Q28: 410 | R28: =Q28*$E28 -> 14555 | T28: =S28*$E28 -> 0 | U28: 439 | V28: 36 | W28: =V28*U28 -> 15804 | Y28: =X28*$E28 -> 0 | AA28: =Z28*$E28 -> 0 | AC28: =AB28*$E28 -> 0 | AE28: =AD28*$E28 -> 0 | AG28: 35.5 | AH28: =AF28*$AG28 -> 0 | AJ28: =AI28*$E28 -> 0 | AL28: =AK28*$E28 -> 0 | AN28: =AM28*$E28 -> 0 | AP28: =AO28*$E28 -> 0 | AR28: =AQ28*$E28 -> 0 | AT28: =AS28*$E28 -> 0 | AV28: =AU28*$E28 -> 0 | AX28: =AW28*$E28 -> 0 | AZ28: =AY28*$E28 -> 0 | BB28: =BA28*$E28 -> 0 | BD28: =BC28*$E28 -> 0 | BF28: =BE28*$E28 -> 0 | BH28: =BG28*$E28 -> 0 | BJ28: =BI28*$E28 -> 0 | BL28: =BK28*$E28 -> 0
B29: =IF(ISBLANK($E29)," ",IF(AND(COUNTA(E$8:$E29)+64>72,COUNTA(E$8:$E29)+64<78),CHAR(COUNTA(E$8:$E29)+65),IF(COUNTA(E$8:$E29)+64>77,CHAR(COUNTA(E$8:$E29)+66),CHAR(COUNTA(E$8:$E29)+64)))) -> M | C29: PA-02I - Porcelain tile 300x300x10mm (L05 - TT table base) | D29: m2 | E29: 4.3 | F29: 233.1 | G29: 932.4 | H29: 890 | I29: 4 | J29: =H29*$I29 -> 3560 | L29: =K29*$E29 -> 0 | N29: =M29*$E29 -> 0 | P29: =O29*$E29 -> 0 | Q29: 380 | R29: =Q29*$E29 -> 1634 | T29: =S29*$E29 -> 0 | U29: 294 | V29: 5 | W29: =V29*U29 -> 1470 | Y29: =X29*$E29 -> 0 | AA29: =Z29*$E29 -> 0 | AC29: =AB29*$E29 -> 0 | AE29: =AD29*$E29 -> 0 | AF29: 418 | AG29: 4.3 | AH29: =AF29*$AG29 -> 1797.4 | AJ29: =AI29*$E29 -> 0 | AL29: =AK29*$E29 -> 0 | AN29: =AM29*$E29 -> 0 | AP29: =AO29*$E29 -> 0 | AR29: =AQ29*$E29 -> 0 | AT29: =AS29*$E29 -> 0 | AV29: =AU29*$E29 -> 0 | AX29: =AW29*$E29 -> 0 | AZ29: =AY29*$E29 -> 0 | BB29: =BA29*$E29 -> 0 | BD29: =BC29*$E29 -> 0 | BF29: =BE29*$E29 -> 0 | BH29: =BG29*$E29 -> 0 | BJ29: =BI29*$E29 -> 0 | BL29: =BK29*$E29 -> 0
B30: =IF(ISBLANK($E30)," ",IF(AND(COUNTA(E$8:$E30)+64>72,COUNTA(E$8:$E30)+64<78),CHAR(COUNTA(E$8:$E30)+65),IF(COUNTA(E$8:$E30)+64>77,CHAR(COUNTA(E$8:$E30)+66),CHAR(COUNTA(E$8:$E30)+64)))) -> N | C30: PA-03 - Pea Gravel - Greige | D30: m2 | E30: 184 | F30: 73.8 | G30: 13579.2 | H30: 166 | I30: 184 | J30: =H30*$I30 -> 30544 | L30: =K30*$E30 -> 0 | N30: =M30*$E30 -> 0 | P30: =O30*$E30 -> 0 | Q30: 185 | R30: =Q30*$E30 -> 34040 | T30: =S30*$E30 -> 0 | U30: 134 | V30: 184 | W30: =V30*U30 -> 24656 | Y30: =X30*$E30 -> 0 | AA30: =Z30*$E30 -> 0 | AC30: =AB30*$E30 -> 0 | AE30: =AD30*$E30 -> 0 | AF30: 152 | AG30: 184 | AH30: =AF30*$AG30 -> 27968 | AJ30: =AI30*$E30 -> 0 | AL30: =AK30*$E30 -> 0 | AN30: =AM30*$E30 -> 0 | AP30: =AO30*$E30 -> 0 | AR30: =AQ30*$E30 -> 0 | AT30: =AS30*$E30 -> 0 | AV30: =AU30*$E30 -> 0 | AX30: =AW30*$E30 -> 0 | AZ30: =AY30*$E30 -> 0 | BB30: =BA30*$E30 -> 0 | BD30: =BC30*$E30 -> 0 | BF30: =BE30*$E30 -> 0 | BH30: =BG30*$E30 -> 0 | BJ30: =BI30*$E30 -> 0 | BL30: =BK30*$E30 -> 0
B31: =IF(ISBLANK($E31)," ",IF(AND(COUNTA(E$8:$E31)+64>72,COUNTA(E$8:$E31)+64<78),CHAR(COUNTA(E$8:$E31)+65),IF(COUNTA(E$8:$E31)+64>77,CHAR(COUNTA(E$8:$E31)+66),CHAR(COUNTA(E$8:$E31)+64)))) -> P | C31: PA-04 - Composite bamboo decking 1850x125x20mm | D31: m2 | E31: 49 | F31: 575.1 | G31: 82239.3 | H31: 1049 | I31: 49 | J31: =H31*$I31 -> 51401 | L31: =K31*$E31 -> 0 | N31: =M31*$E31 -> 0 | P31: =O31*$E31 -> 0 | Q31: 625 | R31: =Q31*$E31 -> 30625 | T31: =S31*$E31 -> 0 | U31: 735 | V31: 143 | W31: =V31*U31 -> 105105 | Y31: =X31*$E31 -> 0 | AA31: =Z31*$E31 -> 0 | AC31: =AB31*$E31 -> 0 | AE31: =AD31*$E31 -> 0 | AF31: 1067 | AG31: 49 | AH31: =AF31*$AG31 -> 52283 | AJ31: =AI31*$E31 -> 0 | AL31: =AK31*$E31 -> 0 | AN31: =AM31*$E31 -> 0 | AP31: =AO31*$E31 -> 0 | AR31: =AQ31*$E31 -> 0 | AT31: =AS31*$E31 -> 0 | AV31: =AU31*$E31 -> 0 | AX31: =AW31*$E31 -> 0 | AZ31: =AY31*$E31 -> 0 | BB31: =BA31*$E31 -> 0 | BD31: =BC31*$E31 -> 0 | BF31: =BE31*$E31 -> 0 | BH31: =BG31*$E31 -> 0 | BJ31: =BI31*$E31 -> 0 | BL31: =BK31*$E31 -> 0
B32: =IF(ISBLANK($E32)," ",IF(AND(COUNTA(E$8:$E32)+64>72,COUNTA(E$8:$E32)+64<78),CHAR(COUNTA(E$8:$E32)+65),IF(COUNTA(E$8:$E32)+64>77,CHAR(COUNTA(E$8:$E32)+66),CHAR(COUNTA(E$8:$E32)+64)))) -> Q | C32: PA-05 - TPV sports Flooring 10mm (L01 - Kids play area Activity zone Outdoor Gym) | D32: m2 | E32: 154 | F32: 520.2 | G32: 80110.8 | H32: 964 | I32: 154 | J32: =H32*$I32 -> 148456 | L32: =K32*$E32 -> 0 | N32: =M32*$E32 -> 0 | P32: =O32*$E32 -> 0 | Q32: 625 | R32: =Q32*$E32 -> 96250 | T32: =S32*$E32 -> 0 | U32: 708 | V32: 154 | W32: =V32*U32 -> 109032 | Y32: =X32*$E32 -> 0 | AA32: =Z32*$E32 -> 0 | AC32: =AB32*$E32 -> 0 | AE32: =AD32*$E32 -> 0 | AF32: 707 | AG32: 154 | AH32: =AF32*$AG32 -> 108878 | AJ32: =AI32*$E32 -> 0 | AL32: =AK32*$E32 -> 0 | AN32: =AM32*$E32 -> 0 | AP32: =AO32*$E32 -> 0 | AR32: =AQ32*$E32 -> 0 | AT32: =AS32*$E32 -> 0 | AV32: =AU32*$E32 -> 0 | AX32: =AW32*$E32 -> 0 | AZ32: =AY32*$E32 -> 0 | BB32: =BA32*$E32 -> 0 | BD32: =BC32*$E32 -> 0 | BF32: =BE32*$E32 -> 0 | BH32: =BG32*$E32 -> 0 | BJ32: =BI32*$E32 -> 0 | BL32: =BK32*$E32 -> 0
B33: =IF(ISBLANK($E33)," ",IF(AND(COUNTA(E$8:$E33)+64>72,COUNTA(E$8:$E33)+64<78),CHAR(COUNTA(E$8:$E33)+65),IF(COUNTA(E$8:$E33)+64>77,CHAR(COUNTA(E$8:$E33)+66),CHAR(COUNTA(E$8:$E33)+64)))) -> R | C33: PA-06 - Decorative Concrete flooring (L01 - Outdoor Dining Area) | D33: m2 | E33: 74 | F33: 684.9 | G33: 51367.5 | H33: 1006 | I33: 74 | J33: =H33*$I33 -> 74444 | L33: =K33*$E33 -> 0 | N33: =M33*$E33 -> 0 | P33: =O33*$E33 -> 0 | Q33: 450 | R33: =Q33*$E33 -> 33300 | T33: =S33*$E33 -> 0 | U33: 863 | V33: 75 | W33: =V33*U33 -> 64725 | Y33: =X33*$E33 -> 0 | AA33: =Z33*$E33 -> 0 | AC33: =AB33*$E33 -> 0 | AE33: =AD33*$E33 -> 0 | AF33: 427 | AG33: 74 | AH33: =AF33*$AG33 -> 31598 | AJ33: =AI33*$E33 -> 0 | AL33: =AK33*$E33 -> 0 | AN33: =AM33*$E33 -> 0 | AP33: =AO33*$E33 -> 0 | AR33: =AQ33*$E33 -> 0 | AT33: =AS33*$E33 -> 0 | AV33: =AU33*$E33 -> 0 | AX33: =AW33*$E33 -> 0 | AZ33: =AY33*$E33 -> 0 | BB33: =BA33*$E33 -> 0 | BD33: =BC33*$E33 -> 0 | BF33: =BE33*$E33 -> 0 | BH33: =BG33*$E33 -> 0 | BJ33: =BI33*$E33 -> 0 | BL33: =BK33*$E33 -> 0
B34: =IF(ISBLANK($E34)," ",IF(AND(COUNTA(E$8:$E34)+64>72,COUNTA(E$8:$E34)+64<78),CHAR(COUNTA(E$8:$E34)+65),IF(COUNTA(E$8:$E34)+64>77,CHAR(COUNTA(E$8:$E34)+66),CHAR(COUNTA(E$8:$E34)+64)))) -> S | C34: PA-07A - Natural stone banding - Honed 200x200x30mm | D34: m2 | E34: 12 | F34: 384.3 | G34: 4995.9 | H34: 959 | I34: 12 | J34: =H34*$I34 -> 11508 | L34: =K34*$E34 -> 0 | N34: =M34*$E34 -> 0 | P34: =O34*$E34 -> 0 | Q34: 620 | R34: =Q34*$E34 -> 7440 | T34: =S34*$E34 -> 0 | U34: 666 | V34: 13 | W34: =V34*U34 -> 8658 | Y34: =X34*$E34 -> 0 | AA34: =Z34*$E34 -> 0 | AC34: =AB34*$E34 -> 0 | AE34: =AD34*$E34 -> 0 | AF34: 572 | AG34: 12 | AH34: =AF34*$AG34 -> 6864 | AJ34: =AI34*$E34 -> 0 | AL34: =AK34*$E34 -> 0 | AN34: =AM34*$E34 -> 0 | AP34: =AO34*$E34 -> 0 | AR34: =AQ34*$E34 -> 0 | AT34: =AS34*$E34 -> 0 | AV34: =AU34*$E34 -> 0 | AX34: =AW34*$E34 -> 0 | AZ34: =AY34*$E34 -> 0 | BB34: =BA34*$E34 -> 0 | BD34: =BC34*$E34 -> 0 | BF34: =BE34*$E34 -> 0 | BH34: =BG34*$E34 -> 0 | BJ34: =BI34*$E34 -> 0 | BL34: =BK34*$E34 -> 0
B35: =IF(ISBLANK($E35)," ",IF(AND(COUNTA(E$8:$E35)+64>72,COUNTA(E$8:$E35)+64<78),CHAR(COUNTA(E$8:$E35)+65),IF(COUNTA(E$8:$E35)+64>77,CHAR(COUNTA(E$8:$E35)+66),CHAR(COUNTA(E$8:$E35)+64)))) -> T | C35: PA-07B - Natural stone flooring - Flamed 100x100x30mm | D35: m2 | E35: 64 | F35: 524.7 | G35: 33580.8 | H35: 1002 | I35: 64 | J35: =H35*$I35 -> 64128 | L35: =K35*$E35 -> 0 | N35: =M35*$E35 -> 0 | P35: =O35*$E35 -> 0 | Q35: 620 | R35: =Q35*$E35 -> 39680 | T35: =S35*$E35 -> 0 | U35: 775 | V35: 64 | W35: =V35*U35 -> 49600 | Y35: =X35*$E35 -> 0 | AA35: =Z35*$E35 -> 0 | AC35: =AB35*$E35 -> 0 | AE35: =AD35*$E35 -> 0 | AF35: 628 | AG35: 64 | AH35: =AF35*$AG35 -> 40192 | AJ35: =AI35*$E35 -> 0 | AL35: =AK35*$E35 -> 0 | AN35: =AM35*$E35 -> 0 | AP35: =AO35*$E35 -> 0 | AR35: =AQ35*$E35 -> 0 | AT35: =AS35*$E35 -> 0 | AV35: =AU35*$E35 -> 0 | AX35: =AW35*$E35 -> 0 | AZ35: =AY35*$E35 -> 0 | BB35: =BA35*$E35 -> 0 | BD35: =BC35*$E35 -> 0 | BF35: =BE35*$E35 -> 0 | BH35: =BG35*$E35 -> 0 | BJ35: =BI35*$E35 -> 0 | BL35: =BK35*$E35 -> 0
B36: =IF(ISBLANK($E36)," ",IF(AND(COUNTA(E$8:$E36)+64>72,COUNTA(E$8:$E36)+64<78),CHAR(COUNTA(E$8:$E36)+65),IF(COUNTA(E$8:$E36)+64>77,CHAR(COUNTA(E$8:$E36)+66),CHAR(COUNTA(E$8:$E36)+64)))) -> U | C36: PA-08 - Silica sand (pet play sand) (L01 - Pet play area) | D36: m2 | E36: 39 | F36: 242.1 | G36: 9684 | H36: 151 | I36: 39 | J36: =H36*$I36 -> 5889 | L36: =K36*$E36 -> 0 | N36: =M36*$E36 -> 0 | P36: =O36*$E36 -> 0 | Q36: 320 | R36: =Q36*$E36 -> 12480 | T36: =S36*$E36 -> 0 | U36: 305 | V36: 40 | W36: =V36*U36 -> 12200 | Y36: =X36*$E36 -> 0 | AA36: =Z36*$E36 -> 0 | AC36: =AB36*$E36 -> 0 | AE36: =AD36*$E36 -> 0 | AF36: 399 | AG36: 39 | AH36: =AF36*$AG36 -> 15561 | AJ36: =AI36*$E36 -> 0 | AL36: =AK36*$E36 -> 0 | AN36: =AM36*$E36 -> 0 | AP36: =AO36*$E36 -> 0 | AR36: =AQ36*$E36 -> 0 | AT36: =AS36*$E36 -> 0 | AV36: =AU36*$E36 -> 0 | AX36: =AW36*$E36 -> 0 | AZ36: =AY36*$E36 -> 0 | BB36: =BA36*$E36 -> 0 | BD36: =BC36*$E36 -> 0 | BF36: =BE36*$E36 -> 0 | BH36: =BG36*$E36 -> 0 | BJ36: =BI36*$E36 -> 0 | BL36: =BK36*$E36 -> 0
B37: =IF(ISBLANK($E37)," ",IF(AND(COUNTA(E$35:$E37)+64>72,COUNTA(E$35:$E37)+64<78),CHAR(COUNTA(E$35:$E37)+65),IF(COUNTA(E$35:$E37)+64>77,CHAR(COUNTA(E$35:$E37)+66),CHAR(COUNTA(E$35:$E37)+64)))) -> C | C37: PA-09 - River pebble - Semi polished.(L05 -Adult Pool Overflow edge) | D37: m2 | E37: 46 | F37: 165.6 | G37: 7617.6 | H37: 457 | I37: 46 | J37: =H37*$I37 -> 21022 | L37: =K37*$E37 -> 0 | N37: =M37*$E37 -> 0 | P37: =O37*$E37 -> 0 | Q37: 410 | R37: =Q37*$E37 -> 18860 | T37: =S37*$E37 -> 0 | U37: 287 | V37: 46 | W37: =V37*U37 -> 13202 | Y37: =X37*$E37 -> 0 | AA37: =Z37*$E37 -> 0 | AC37: =AB37*$E37 -> 0 | AE37: =AD37*$E37 -> 0 | AG37: 46 | AH37: =AF37*$AG37 -> 0 | AJ37: =AI37*$E37 -> 0 | AL37: =AK37*$E37 -> 0 | AN37: =AM37*$E37 -> 0 | AP37: =AO37*$E37 -> 0 | AR37: =AQ37*$E37 -> 0 | AT37: =AS37*$E37 -> 0 | AV37: =AU37*$E37 -> 0 | AX37: =AW37*$E37 -> 0 | AZ37: =AY37*$E37 -> 0 | BB37: =BA37*$E37 -> 0 | BD37: =BC37*$E37 -> 0 | BF37: =BE37*$E37 -> 0 | BH37: =BG37*$E37 -> 0 | BJ37: =BI37*$E37 -> 0 | BL37: =BK37*$E37 -> 0
B38: =IF(ISBLANK($E38)," ",IF(AND(COUNTA(E$35:$E38)+64>72,COUNTA(E$35:$E38)+64<78),CHAR(COUNTA(E$35:$E38)+65),IF(COUNTA(E$35:$E38)+64>77,CHAR(COUNTA(E$35:$E38)+66),CHAR(COUNTA(E$35:$E38)+64)))) -> D | C38: W-01 - Wall coping tile 200x600x20 | D38: m | E38: 423 | F38: 84.6 | G38: 45514.8 | H38: 752 | I38: 423 | J38: =H38*$I38 -> 318096 | L38: =K38*$E38 -> 0 | N38: =M38*$E38 -> 0 | P38: =O38*$E38 -> 0 | Q38: 385 | R38: =Q38*$E38 -> 162855 | T38: =S38*$E38 -> 0 | U38: 106 | V38: 538 | W38: =V38*U38 -> 57028 | Y38: =X38*$E38 -> 0 | AA38: =Z38*$E38 -> 0 | AC38: =AB38*$E38 -> 0 | AE38: =AD38*$E38 -> 0 | AF38: 188 | AG38: 423 | AH38: =AF38*$AG38 -> 79524 | AJ38: =AI38*$E38 -> 0 | AL38: =AK38*$E38 -> 0 | AN38: =AM38*$E38 -> 0 | AP38: =AO38*$E38 -> 0 | AR38: =AQ38*$E38 -> 0 | AT38: =AS38*$E38 -> 0 | AV38: =AU38*$E38 -> 0 | AX38: =AW38*$E38 -> 0 | AZ38: =AY38*$E38 -> 0 | BB38: =BA38*$E38 -> 0 | BD38: =BC38*$E38 -> 0 | BF38: =BE38*$E38 -> 0 | BH38: =BG38*$E38 -> 0 | BJ38: =BI38*$E38 -> 0 | BL38: =BK38*$E38 -> 0
B39: =IF(ISBLANK($E39)," ",IF(AND(COUNTA(E$35:$E39)+64>72,COUNTA(E$35:$E39)+64<78),CHAR(COUNTA(E$35:$E39)+65),IF(COUNTA(E$35:$E39)+64>77,CHAR(COUNTA(E$35:$E39)+66),CHAR(COUNTA(E$35:$E39)+64)))) -> E | C39: W-02 - Porcelain wall tile 600x600x10mm | D39: m2 | E39: 320 | F39: 249.3 | G39: 79776 | H39: 458 | I39: 320 | J39: =H39*$I39 -> 146560 | L39: =K39*$E39 -> 0 | N39: =M39*$E39 -> 0 | P39: =O39*$E39 -> 0 | Q39: 385 | R39: =Q39*$E39 -> 123200 | T39: =S39*$E39 -> 0 | U39: 329 | V39: 320 | W39: =V39*U39 -> 105280 | Y39: =X39*$E39 -> 0 | AA39: =Z39*$E39 -> 0 | AC39: =AB39*$E39 -> 0 | AE39: =AD39*$E39 -> 0 | AF39: 404 | AG39: 320 | AH39: =AF39*$AG39 -> 129280 | AJ39: =AI39*$E39 -> 0 | AL39: =AK39*$E39 -> 0 | AN39: =AM39*$E39 -> 0 | AP39: =AO39*$E39 -> 0 | AR39: =AQ39*$E39 -> 0 | AT39: =AS39*$E39 -> 0 | AV39: =AU39*$E39 -> 0 | AX39: =AW39*$E39 -> 0 | AZ39: =AY39*$E39 -> 0 | BB39: =BA39*$E39 -> 0 | BD39: =BC39*$E39 -> 0 | BF39: =BE39*$E39 -> 0 | BH39: =BG39*$E39 -> 0 | BJ39: =BI39*$E39 -> 0 | BL39: =BK39*$E39 -> 0
B40: ADD | C40: W-02 - Porcelain wall tile 600x600x10mm | D40: m2 | E40: 8 | R40: =Q40*$E40 -> 0 | T40: =S40*$E40 -> 0 | U40: 328 | V40: 8 | W40: =V40*U40 -> 2624 | AF40: 572 | AG40: 8 | AH40: =AF40*$AG40 -> 4576
B41: =IF(ISBLANK($E41)," ",IF(AND(COUNTA(E$35:$E41)+64>72,COUNTA(E$35:$E41)+64<78),CHAR(COUNTA(E$35:$E41)+65),IF(COUNTA(E$35:$E41)+64>77,CHAR(COUNTA(E$35:$E41)+66),CHAR(COUNTA(E$35:$E41)+64)))) -> G | C41: WA-01 - Outdoor wallpaper (kids play area) | D41: m | E41: 18 | F41: 3427.2 | G41: 61689.6 | I41: 18 | J41: =H41*$I41 -> 0 | L41: =K41*$E41 -> 0 | N41: =M41*$E41 -> 0 | P41: =O41*$E41 -> 0 | Q41: 795 | R41: =Q41*$E41 -> 14310 | T41: =S41*$E41 -> 0 | V41: 18 | W41: =V41*U41 -> 0 | Y41: =X41*$E41 -> 0 | AA41: =Z41*$E41 -> 0 | AC41: =AB41*$E41 -> 0 | AE41: =AD41*$E41 -> 0 | AG41: 18 | AH41: =AF41*$AG41 -> 0 | AJ41: =AI41*$E41 -> 0 | AL41: =AK41*$E41 -> 0 | AN41: =AM41*$E41 -> 0 | AP41: =AO41*$E41 -> 0 | AR41: =AQ41*$E41 -> 0 | AT41: =AS41*$E41 -> 0 | AV41: =AU41*$E41 -> 0 | AX41: =AW41*$E41 -> 0 | AZ41: =AY41*$E41 -> 0 | BB41: =BA41*$E41 -> 0 | BD41: =BC41*$E41 -> 0 | BF41: =BE41*$E41 -> 0 | BH41: =BG41*$E41 -> 0 | BJ41: =BI41*$E41 -> 0 | BL41: =BK41*$E41 -> 0
B42: =IF(ISBLANK($E42)," ",IF(AND(COUNTA(E$35:$E42)+64>72,COUNTA(E$35:$E42)+64<78),CHAR(COUNTA(E$35:$E42)+65),IF(COUNTA(E$35:$E42)+64>77,CHAR(COUNTA(E$35:$E42)+66),CHAR(COUNTA(E$35:$E42)+64)))) -> H | C42: WA-02 - Graffiti Art | D42: m | E42: 18 | F42: 225 | G42: 4050 | I42: 18 | J42: =H42*$I42 -> 0 | L42: =K42*$E42 -> 0 | N42: =M42*$E42 -> 0 | P42: =O42*$E42 -> 0 | Q42: 1200 | R42: =Q42*$E42 -> 21600 | T42: =S42*$E42 -> 0 | V42: 8 | W42: =V42*U42 -> 0 | Y42: =X42*$E42 -> 0 | AA42: =Z42*$E42 -> 0 | AC42: =AB42*$E42 -> 0 | AE42: =AD42*$E42 -> 0 | AG42: 18 | AH42: =AF42*$AG42 -> 0 | AJ42: =AI42*$E42 -> 0 | AL42: =AK42*$E42 -> 0 | AN42: =AM42*$E42 -> 0 | AP42: =AO42*$E42 -> 0 | AR42: =AQ42*$E42 -> 0 | AT42: =AS42*$E42 -> 0 | AV42: =AU42*$E42 -> 0 | AX42: =AW42*$E42 -> 0 | AZ42: =AY42*$E42 -> 0 | BB42: =BA42*$E42 -> 0 | BD42: =BC42*$E42 -> 0 | BF42: =BE42*$E42 -> 0 | BH42: =BG42*$E42 -> 0 | BJ42: =BI42*$E42 -> 0 | BL42: =BK42*$E42 -> 0
B43: =IF(ISBLANK($E43)," ",IF(AND(COUNTA(E$35:$E43)+64>72,COUNTA(E$35:$E43)+64<78),CHAR(COUNTA(E$35:$E43)+65),IF(COUNTA(E$35:$E43)+64>77,CHAR(COUNTA(E$35:$E43)+66),CHAR(COUNTA(E$35:$E43)+64)))) -> J | C43: F-01 - Treated timber | D43: m2 | E43: 44 | F43: 2621.7 | G43: 44568.9 | H43: 1100 | I43: 44 | J43: =H43*$I43 -> 48400 | L43: =K43*$E43 -> 0 | N43: =M43*$E43 -> 0 | P43: =O43*$E43 -> 0 | Q43: 725 | R43: =Q43*$E43 -> 31900 | T43: =S43*$E43 -> 0 | U43: 3306 | V43: 17 | W43: =V43*U43 -> 56202 | Y43: =X43*$E43 -> 0 | AA43: =Z43*$E43 -> 0 | AC43: =AB43*$E43 -> 0 | AE43: =AD43*$E43 -> 0 | AF43: 934 | AG43: 44 | AH43: =AF43*$AG43 -> 41096 | AJ43: =AI43*$E43 -> 0 | AL43: =AK43*$E43 -> 0 | AN43: =AM43*$E43 -> 0 | AP43: =AO43*$E43 -> 0 | AR43: =AQ43*$E43 -> 0 | AT43: =AS43*$E43 -> 0 | AV43: =AU43*$E43 -> 0 | AX43: =AW43*$E43 -> 0 | AZ43: =AY43*$E43 -> 0 | BB43: =BA43*$E43 -> 0 | BD43: =BC43*$E43 -> 0 | BF43: =BE43*$E43 -> 0 | BH43: =BG43*$E43 -> 0 | BJ43: =BI43*$E43 -> 0 | BL43: =BK43*$E43 -> 0
B44: =IF(ISBLANK($E44)," ",IF(AND(COUNTA(E$35:$E44)+64>72,COUNTA(E$35:$E44)+64<78),CHAR(COUNTA(E$35:$E44)+65),IF(COUNTA(E$35:$E44)+64>77,CHAR(COUNTA(E$35:$E44)+66),CHAR(COUNTA(E$35:$E44)+64)))) -> K | C44: F-02A - Powder coating on Aluminium railing 1200mm high | D44: m | E44: 23 | F44: 952.2 | G44: 21900.6 | H44: 2164 | I44: 44 | J44: =H44*$I44 -> 95216 | L44: =K44*$E44 -> 0 | N44: =M44*$E44 -> 0 | P44: =O44*$E44 -> 0 | Q44: 2950 | R44: =Q44*$E44 -> 67850 | T44: =S44*$E44 -> 0 | V44: 23 | W44: =V44*U44 -> 0 | Y44: =X44*$E44 -> 0 | AA44: =Z44*$E44 -> 0 | AC44: =AB44*$E44 -> 0 | AE44: =AD44*$E44 -> 0 | AF44: 1187 | AG44: 23 | AH44: =AF44*$AG44 -> 27301 | AJ44: =AI44*$E44 -> 0 | AL44: =AK44*$E44 -> 0 | AN44: =AM44*$E44 -> 0 | AP44: =AO44*$E44 -> 0 | AR44: =AQ44*$E44 -> 0 | AT44: =AS44*$E44 -> 0 | AV44: =AU44*$E44 -> 0 | AX44: =AW44*$E44 -> 0 | AZ44: =AY44*$E44 -> 0 | BB44: =BA44*$E44 -> 0 | BD44: =BC44*$E44 -> 0 | BF44: =BE44*$E44 -> 0 | BH44: =BG44*$E44 -> 0 | BJ44: =BI44*$E44 -> 0 | BL44: =BK44*$E44 -> 0
B45: =IF(ISBLANK($E45)," ",IF(AND(COUNTA(E$35:$E45)+64>72,COUNTA(E$35:$E45)+64<78),CHAR(COUNTA(E$35:$E45)+65),IF(COUNTA(E$35:$E45)+64>77,CHAR(COUNTA(E$35:$E45)+66),CHAR(COUNTA(E$35:$E45)+64)))) -> L | C45: F-02B - Powder coating on Aluminium - wooden pattern (L05 -Barbeque Area) | D45: m2 | E45: 4 | F45: 952.2 | G45: 3808.8 | H45: 5021 | I45: 4 | J45: =H45*$I45 -> 20084 | L45: =K45*$E45 -> 0 | N45: =M45*$E45 -> 0 | P45: =O45*$E45 -> 0 | Q45: 3750 | R45: =Q45*$E45 -> 15000 | T45: =S45*$E45 -> 0 | V45: 4 | W45: =V45*U45 -> 0 | Y45: =X45*$E45 -> 0 | AA45: =Z45*$E45 -> 0 | AC45: =AB45*$E45 -> 0 | AE45: =AD45*$E45 -> 0 | AF45: 3254 | AG45: 4 | AH45: =AF45*$AG45 -> 13016 | AJ45: =AI45*$E45 -> 0 | AL45: =AK45*$E45 -> 0 | AN45: =AM45*$E45 -> 0 | AP45: =AO45*$E45 -> 0 | AR45: =AQ45*$E45 -> 0 | AT45: =AS45*$E45 -> 0 | AV45: =AU45*$E45 -> 0 | AX45: =AW45*$E45 -> 0 | AZ45: =AY45*$E45 -> 0 | BB45: =BA45*$E45 -> 0 | BD45: =BC45*$E45 -> 0 | BF45: =BE45*$E45 -> 0 | BH45: =BG45*$E45 -> 0 | BJ45: =BI45*$E45 -> 0 | BL45: =BK45*$E45 -> 0
B46: =IF(ISBLANK($E46)," ",IF(AND(COUNTA(E$35:$E46)+64>72,COUNTA(E$35:$E46)+64<78),CHAR(COUNTA(E$35:$E46)+65),IF(COUNTA(E$35:$E46)+64>77,CHAR(COUNTA(E$35:$E46)+66),CHAR(COUNTA(E$35:$E46)+64)))) -> M | C46: F-03 - Water based acrylic paint texture | D46: m2 | E46: 40 | F46: 47.7 | G46: 1908 | H46: 107 | I46: 40 | J46: =H46*$I46 -> 4280 | L46: =K46*$E46 -> 0 | N46: =M46*$E46 -> 0 | P46: =O46*$E46 -> 0 | Q46: 320 | R46: =Q46*$E46 -> 12800 | T46: =S46*$E46 -> 0 | V46: 41 | W46: =V46*U46 -> 0 | Y46: =X46*$E46 -> 0 | AA46: =Z46*$E46 -> 0 | AC46: =AB46*$E46 -> 0 | AE46: =AD46*$E46 -> 0 | AG46: 40 | AH46: =AF46*$AG46 -> 0 | AJ46: =AI46*$E46 -> 0 | AL46: =AK46*$E46 -> 0 | AN46: =AM46*$E46 -> 0 | AP46: =AO46*$E46 -> 0 | AR46: =AQ46*$E46 -> 0 | AT46: =AS46*$E46 -> 0 | AV46: =AU46*$E46 -> 0 | AX46: =AW46*$E46 -> 0 | AZ46: =AY46*$E46 -> 0 | BB46: =BA46*$E46 -> 0 | BD46: =BC46*$E46 -> 0 | BF46: =BE46*$E46 -> 0 | BH46: =BG46*$E46 -> 0 | BJ46: =BI46*$E46 -> 0 | BL46: =BK46*$E46 -> 0
B47: =IF(ISBLANK($E47)," ",IF(AND(COUNTA(E$35:$E47)+64>72,COUNTA(E$35:$E47)+64<78),CHAR(COUNTA(E$35:$E47)+65),IF(COUNTA(E$35:$E47)+64>77,CHAR(COUNTA(E$35:$E47)+66),CHAR(COUNTA(E$35:$E47)+64)))) -> N | C47: F-04 - Cast Stone seats | D47: m2 | E47: 31 | F47: 3965.4 | G47: 162581.4 | H47: 2964 | I47: 31 | J47: =H47*$I47 -> 91884 | L47: =K47*$E47 -> 0 | N47: =M47*$E47 -> 0 | P47: =O47*$E47 -> 0 | Q47: 3100 | R47: =Q47*$E47 -> 96100 | T47: =S47*$E47 -> 0 | U47: 5751 | V47: 42 | W47: =V47*U47 -> 241542 | Y47: =X47*$E47 -> 0 | AA47: =Z47*$E47 -> 0 | AC47: =AB47*$E47 -> 0 | AE47: =AD47*$E47 -> 0 | AF47: 3334 | AG47: 31 | AH47: =AF47*$AG47 -> 103354 | AJ47: =AI47*$E47 -> 0 | AL47: =AK47*$E47 -> 0 | AN47: =AM47*$E47 -> 0 | AP47: =AO47*$E47 -> 0 | AR47: =AQ47*$E47 -> 0 | AT47: =AS47*$E47 -> 0 | AV47: =AU47*$E47 -> 0 | AX47: =AW47*$E47 -> 0 | AZ47: =AY47*$E47 -> 0 | BB47: =BA47*$E47 -> 0 | BD47: =BC47*$E47 -> 0 | BF47: =BE47*$E47 -> 0 | BH47: =BG47*$E47 -> 0 | BJ47: =BI47*$E47 -> 0 | BL47: =BK47*$E47 -> 0
B48: =IF(ISBLANK($E48)," ",IF(AND(COUNTA(E$35:$E48)+64>72,COUNTA(E$35:$E48)+64<78),CHAR(COUNTA(E$35:$E48)+65),IF(COUNTA(E$35:$E48)+64>77,CHAR(COUNTA(E$35:$E48)+66),CHAR(COUNTA(E$35:$E48)+64)))) -> P | C48: F-04 - Cast Stone Pebbles (1800x400mm) | D48: No | E48: 1 | F48: 4094.1 | G48: 32752.8 | H48: 4371 | I48: 1 | J48: =H48*$I48 -> 4371 | L48: =K48*$E48 -> 0 | N48: =M48*$E48 -> 0 | P48: =O48*$E48 -> 0 | Q48: 7500 | R48: =Q48*$E48 -> 7500 | T48: =S48*$E48 -> 0 | U48: 5913 | V48: 8 | W48: =V48*U48 -> 47304 | Y48: =X48*$E48 -> 0 | AA48: =Z48*$E48 -> 0 | AC48: =AB48*$E48 -> 0 | AE48: =AD48*$E48 -> 0 | AF48: 4934 | AG48: 1 | AH48: =AF48*$AG48 -> 4934 | AJ48: =AI48*$E48 -> 0 | AL48: =AK48*$E48 -> 0 | AN48: =AM48*$E48 -> 0 | AP48: =AO48*$E48 -> 0 | AR48: =AQ48*$E48 -> 0 | AT48: =AS48*$E48 -> 0 | AV48: =AU48*$E48 -> 0 | AX48: =AW48*$E48 -> 0 | AZ48: =AY48*$E48 -> 0 | BB48: =BA48*$E48 -> 0 | BD48: =BC48*$E48 -> 0 | BF48: =BE48*$E48 -> 0 | BH48: =BG48*$E48 -> 0 | BJ48: =BI48*$E48 -> 0 | BL48: =BK48*$E48 -> 0
B49: =IF(ISBLANK($E49)," ",IF(AND(COUNTA(E$35:$E49)+64>72,COUNTA(E$35:$E49)+64<78),CHAR(COUNTA(E$35:$E49)+65),IF(COUNTA(E$35:$E49)+64>77,CHAR(COUNTA(E$35:$E49)+66),CHAR(COUNTA(E$35:$E49)+64)))) -> Q | C49: F-05 - (2m2) - Waterproofing membrane (This is shade structure as per the schedule) | D49: No | E49: 1 | F49: 23785.2 | G49: 47570.4 | H49: 1933 | I49: 1 | J49: =H49*$I49 -> 1933 | L49: =K49*$E49 -> 0 | N49: =M49*$E49 -> 0 | P49: =O49*$E49 -> 0 | R49: =Q49*$E49 -> 0 | T49: =S49*$E49 -> 0 | V49: 1 | W49: =V49*U49 -> 0 | Y49: =X49*$E49 -> 0 | AA49: =Z49*$E49 -> 0 | AC49: =AB49*$E49 -> 0 | AE49: =AD49*$E49 -> 0 | AF49: 2460 | AG49: 1 | AH49: =AF49*$AG49 -> 2460 | AJ49: =AI49*$E49 -> 0 | AL49: =AK49*$E49 -> 0 | AN49: =AM49*$E49 -> 0 | AP49: =AO49*$E49 -> 0 | AR49: =AQ49*$E49 -> 0 | AT49: =AS49*$E49 -> 0 | AV49: =AU49*$E49 -> 0 | AX49: =AW49*$E49 -> 0 | AZ49: =AY49*$E49 -> 0 | BB49: =BA49*$E49 -> 0 | BD49: =BC49*$E49 -> 0 | BF49: =BE49*$E49 -> 0 | BH49: =BG49*$E49 -> 0 | BJ49: =BI49*$E49 -> 0 | BL49: =BK49*$E49 -> 0
B50: ADD | C50: F-09 Treated Timber Lumber | D50: No | E50: 1 | R50: =Q50*$E50 -> 0 | T50: =S50*$E50 -> 0 | U50: 44850 | V50: 1 | W50: =V50*U50 -> 44850 | AG50: 1
B51: ADD | C51: F-10 Acrylic Fabric | D51: No | E51: 1 | R51: =Q51*$E51 -> 0 | T51: =S51*$E51 -> 0 | V51: 1 | W51: =V51*U51 -> 0 | AG51: 1
B52: =IF(ISBLANK($E52)," ",IF(AND(COUNTA(E$35:$E52)+64>72,COUNTA(E$35:$E52)+64<78),CHAR(COUNTA(E$35:$E52)+65),IF(COUNTA(E$35:$E52)+64>77,CHAR(COUNTA(E$35:$E52)+66),CHAR(COUNTA(E$35:$E52)+64)))) -> T | C52: BB-01 - Concrete breeze blocks 150x150x200mm | D52: m2 | E52: 3 | F52: 1257.3 | G52: 15087.6 | H52: 17893 | I52: 3 | J52: =H52*$I52 -> 53679 | L52: =K52*$E52 -> 0 | N52: =M52*$E52 -> 0 | P52: =O52*$E52 -> 0 | Q52: 1850 | R52: =Q52*$E52 -> 5550 | T52: =S52*$E52 -> 0 | U52: 1585 | V52: 12 | W52: =V52*U52 -> 19020 | Y52: =X52*$E52 -> 0 | AA52: =Z52*$E52 -> 0 | AC52: =AB52*$E52 -> 0 | AE52: =AD52*$E52 -> 0 | AG52: 3 | AH52: =AF52*$AG52 -> 0 | AJ52: =AI52*$E52 -> 0 | AL52: =AK52*$E52 -> 0 | AN52: =AM52*$E52 -> 0 | AP52: =AO52*$E52 -> 0 | AR52: =AQ52*$E52 -> 0 | AT52: =AS52*$E52 -> 0 | AV52: =AU52*$E52 -> 0 | AX52: =AW52*$E52 -> 0 | AZ52: =AY52*$E52 -> 0 | BB52: =BA52*$E52 -> 0 | BD52: =BC52*$E52 -> 0 | BF52: =BE52*$E52 -> 0 | BH52: =BG52*$E52 -> 0 | BJ52: =BI52*$E52 -> 0 | BL52: =BK52*$E52 -> 0
B53: ADD | C53: E-01- Bike repair station | D53: No | E53: 1 | V53: 1 | W53: =V53*U53 -> 0 | AG53: 1
B54: =IF(ISBLANK($E54)," ",IF(AND(COUNTA(E$35:$E54)+64>72,COUNTA(E$35:$E54)+64<78),CHAR(COUNTA(E$35:$E54)+65),IF(COUNTA(E$35:$E54)+64>77,CHAR(COUNTA(E$35:$E54)+66),CHAR(COUNTA(E$35:$E54)+64)))) -> V | C54: E-02 -Bike rack | D54: m | E54: 16 | F54: 812 | G54: 12992 | H54: 3123 | I54: 16 | J54: =H54*$I54 -> 49968 | L54: =K54*$E54 -> 0 | N54: =M54*$E54 -> 0 | P54: =O54*$E54 -> 0 | Q54: 2850 | R54: =Q54*$E54 -> 45600 | T54: =S54*$E54 -> 0 | V54: 16 | W54: =V54*U54 -> 0 | Y54: =X54*$E54 -> 0 | AA54: =Z54*$E54 -> 0 | AC54: =AB54*$E54 -> 0 | AE54: =AD54*$E54 -> 0 | AF54: 3114 | AG54: 16 | AH54: =AF54*$AG54 -> 49824 | AJ54: =AI54*$E54 -> 0 | AL54: =AK54*$E54 -> 0 | AN54: =AM54*$E54 -> 0 | AP54: =AO54*$E54 -> 0 | AR54: =AQ54*$E54 -> 0 | AT54: =AS54*$E54 -> 0 | AV54: =AU54*$E54 -> 0 | AX54: =AW54*$E54 -> 0 | AZ54: =AY54*$E54 -> 0 | BB54: =BA54*$E54 -> 0 | BD54: =BC54*$E54 -> 0 | BF54: =BE54*$E54 -> 0 | BH54: =BG54*$E54 -> 0 | BJ54: =BI54*$E54 -> 0 | BL54: =BK54*$E54 -> 0
B55: =IF(ISBLANK($E55)," ",IF(AND(COUNTA(E$35:$E55)+64>72,COUNTA(E$35:$E55)+64<78),CHAR(COUNTA(E$35:$E55)+65),IF(COUNTA(E$35:$E55)+64>77,CHAR(COUNTA(E$35:$E55)+66),CHAR(COUNTA(E$35:$E55)+64)))) -> W | C55: E-04 - Metal edge trim | D55: m | E55: 123 | F55: 108.9 | G55: 23740.2 | H55: 196 | I55: 123 | J55: =H55*$I55 -> 24108 | L55: =K55*$E55 -> 0 | N55: =M55*$E55 -> 0 | P55: =O55*$E55 -> 0 | Q55: 185 | R55: =Q55*$E55 -> 22755 | T55: =S55*$E55 -> 0 | U55: 137 | V55: 218 | W55: =V55*U55 -> 29866 | Y55: =X55*$E55 -> 0 | AA55: =Z55*$E55 -> 0 | AC55: =AB55*$E55 -> 0 | AE55: =AD55*$E55 -> 0 | AF55: 87 | AG55: 123 | AH55: =AF55*$AG55 -> 10701 | AJ55: =AI55*$E55 -> 0 | AL55: =AK55*$E55 -> 0 | AN55: =AM55*$E55 -> 0 | AP55: =AO55*$E55 -> 0 | AR55: =AQ55*$E55 -> 0 | AT55: =AS55*$E55 -> 0 | AV55: =AU55*$E55 -> 0 | AX55: =AW55*$E55 -> 0 | AZ55: =AY55*$E55 -> 0 | BB55: =BA55*$E55 -> 0 | BD55: =BC55*$E55 -> 0 | BF55: =BE55*$E55 -> 0 | BH55: =BG55*$E55 -> 0 | BJ55: =BI55*$E55 -> 0 | BL55: =BK55*$E55 -> 0
C56: Trellis including all supports and louvers | D56: m2 | E56: 28 | F56: 9576 | G56: 268128 | I56: 28 | J56: =H56*$I56 -> 0 | L56: =K56*$E56 -> 0 | N56: =M56*$E56 -> 0 | P56: =O56*$E56 -> 0 | Q56: 2250 | R56: =Q56*$E56 -> 63000 | T56: =S56*$E56 -> 0 | V56: 52 | W56: =V56*U56 -> 0 | Y56: =X56*$E56 -> 0 | AA56: =Z56*$E56 -> 0 | AC56: =AB56*$E56 -> 0 | AE56: =AD56*$E56 -> 0 | AG56: 28 | AH56: =AF56*$AG56 -> 0 | AJ56: =AI56*$E56 -> 0 | AL56: =AK56*$E56 -> 0 | AN56: =AM56*$E56 -> 0 | AP56: =AO56*$E56 -> 0 | AR56: =AQ56*$E56 -> 0 | AT56: =AS56*$E56 -> 0 | AV56: =AU56*$E56 -> 0 | AX56: =AW56*$E56 -> 0 | AZ56: =AY56*$E56 -> 0 | BB56: =BA56*$E56 -> 0 | BD56: =BC56*$E56 -> 0 | BF56: =BE56*$E56 -> 0 | BH56: =BG56*$E56 -> 0 | BJ56: =BI56*$E56 -> 0 | BL56: =BK56*$E56 -> 0
C57: Pods canopy - Overall size 2800x1910x2320mm | D57: No | E57: 1 | F57: 18956.7 | G57: 37913.4 | H57: 149297 | I57: 1 | J57: =H57*$I57 -> 149297 | L57: =K57*$E57 -> 0 | N57: =M57*$E57 -> 0 | P57: =O57*$E57 -> 0 | Q57: 48000 | R57: =Q57*$E57 -> 48000 | T57: =S57*$E57 -> 0 | V57: 2 | W57: =V57*U57 -> 0 | Y57: =X57*$E57 -> 0 | AA57: =Z57*$E57 -> 0 | AC57: =AB57*$E57 -> 0 | AE57: =AD57*$E57 -> 0 | AF57: 36587 | AG57: 1 | AH57: =AF57*$AG57 -> 36587 | AJ57: =AI57*$E57 -> 0 | AL57: =AK57*$E57 -> 0 | AN57: =AM57*$E57 -> 0 | AP57: =AO57*$E57 -> 0 | AR57: =AQ57*$E57 -> 0 | AT57: =AS57*$E57 -> 0 | AV57: =AU57*$E57 -> 0 | AX57: =AW57*$E57 -> 0 | AZ57: =AY57*$E57 -> 0 | BB57: =BA57*$E57 -> 0 | BD57: =BC57*$E57 -> 0 | BF57: =BE57*$E57 -> 0 | BH57: =BG57*$E57 -> 0 | BJ57: =BI57*$E57 -> 0 | BL57: =BK57*$E57 -> 0
C58: Pods canopy - Overall size 1670x1350x2180mm | D58: No | E58: 1 | F58: 18956.7 | G58: 37913.4 | H58: 137640 | I58: 1 | J58: =H58*$I58 -> 137640 | L58: =K58*$E58 -> 0 | N58: =M58*$E58 -> 0 | P58: =O58*$E58 -> 0 | Q58: 43500 | R58: =Q58*$E58 -> 43500 | T58: =S58*$E58 -> 0 | V58: 2 | W58: =V58*U58 -> 0 | Y58: =X58*$E58 -> 0 | AA58: =Z58*$E58 -> 0 | AC58: =AB58*$E58 -> 0 | AE58: =AD58*$E58 -> 0 | AF58: 26667 | AG58: 1 | AH58: =AF58*$AG58 -> 26667 | AJ58: =AI58*$E58 -> 0 | AL58: =AK58*$E58 -> 0 | AN58: =AM58*$E58 -> 0 | AP58: =AO58*$E58 -> 0 | AR58: =AQ58*$E58 -> 0 | AT58: =AS58*$E58 -> 0 | AV58: =AU58*$E58 -> 0 | AX58: =AW58*$E58 -> 0 | AZ58: =AY58*$E58 -> 0 | BB58: =BA58*$E58 -> 0 | BD58: =BC58*$E58 -> 0 | BF58: =BE58*$E58 -> 0 | BH58: =BG58*$E58 -> 0 | BJ58: =BI58*$E58 -> 0 | BL58: =BK58*$E58 -> 0
C59: E17 Landscape Edger | D59: m | E59: 10.4 | F59: 83.7 | G59: 870.48 | H59: 163 | I59: 1 | J59: =H59*$I59 -> 163 | L59: =K59*$E59 -> 0 | N59: =M59*$E59 -> 0 | P59: =O59*$E59 -> 0 | Q59: 230 | R59: =Q59*$E59 -> 2392 | T59: =S59*$E59 -> 0 | U59: 105 | V59: 10 | W59: =V59*U59 -> 1050 | Y59: =X59*$E59 -> 0 | AA59: =Z59*$E59 -> 0 | AC59: =AB59*$E59 -> 0 | AE59: =AD59*$E59 -> 0 | AF59: 103 | AG59: 10.4 | AH59: =AF59*$AG59 -> 1071.2 | AJ59: =AI59*$E59 -> 0 | AL59: =AK59*$E59 -> 0 | AN59: =AM59*$E59 -> 0 | AP59: =AO59*$E59 -> 0 | AR59: =AQ59*$E59 -> 0 | AT59: =AS59*$E59 -> 0 | AV59: =AU59*$E59 -> 0 | AX59: =AW59*$E59 -> 0 | AZ59: =AY59*$E59 -> 0 | BB59: =BA59*$E59 -> 0 | BD59: =BC59*$E59 -> 0 | BF59: =BE59*$E59 -> 0 | BH59: =BG59*$E59 -> 0 | BJ59: =BI59*$E59 -> 0 | BL59: =BK59*$E59 -> 0
C60: SOFTSCAPE | F60: 0 | G60: 0 | BK60: unbonded
B61: =IF(ISBLANK($E61)," ",IF(AND(COUNTA(E$8:$E61)+64>72,COUNTA(E$8:$E61)+64<78),CHAR(COUNTA(E$8:$E61)+65),IF(COUNTA(E$8:$E61)+64>77,CHAR(COUNTA(E$8:$E61)+66),CHAR(COUNTA(E$8:$E61)+64)))) | C61: Trees & Plantings Procure and plant in position of following trees & Plantings including necessary excavation from rough grade, transferring, drain cell layer, waterproofing,planting medium, geotextile member, mulching and all necessary, complete; all in accordance with the Drawings and Specification Trees
B62: =IF(ISBLANK($E62)," ",IF(AND(COUNTA(E$59:$E62)+64>72,COUNTA(E$59:$E62)+64<78),CHAR(COUNTA(E$59:$E62)+65),IF(COUNTA(E$59:$E62)+64>77,CHAR(COUNTA(E$59:$E62)+66),CHAR(COUNTA(E$59:$E62)+64)))) -> B | C62: T/PAND-UT - Pandanus utilis - Screw pine | D62: No | E62: 14 | F62: 3431.7 | G62: 48043.8 | H62: 6772 | I62: 14 | J62: =H62*$I62 -> 94808 | L62: =K62*$E62 -> 0 | N62: =M62*$E62 -> 0 | P62: =O62*$E62 -> 0 | Q62: 2900 | R62: =Q62*$E62 -> 40600 | T62: =S62*$E62 -> 0 | U62: 4072 | V62: 14 | W62: =U62*$V62 -> 57008 | Y62: =X62*$E62 -> 0 | AA62: =Z62*$E62 -> 0 | AC62: =AB62*$E62 -> 0 | AE62: =AD62*$E62 -> 0 | AF62: 1578 | AG62: 14 | AH62: =AF62*$AG62 -> 22092 | AJ62: =AI62*$E62 -> 0 | AL62: =AK62*$E62 -> 0 | AN62: =AM62*$E62 -> 0 | AP62: =AO62*$E62 -> 0 | AR62: =AQ62*$E62 -> 0 | AT62: =AS62*$E62 -> 0 | AV62: =AU62*$E62 -> 0 | AX62: =AW62*$E62 -> 0 | AZ62: =AY62*$E62 -> 0 | BB62: =BA62*$E62 -> 0 | BD62: =BC62*$E62 -> 0 | BF62: =BE62*$E62 -> 0 | BH62: =BG62*$E62 -> 0 | BJ62: =BI62*$E62 -> 0 | BL62: =BK62*$E62 -> 0
B63: =IF(ISBLANK($E63)," ",IF(AND(COUNTA(E$59:$E63)+64>72,COUNTA(E$59:$E63)+64<78),CHAR(COUNTA(E$59:$E63)+65),IF(COUNTA(E$59:$E63)+64>77,CHAR(COUNTA(E$59:$E63)+66),CHAR(COUNTA(E$59:$E63)+64)))) -> C | C63: T/DELO-RE - Delonix regia - Flame tree | D63: No | E63: 1 | F63: 2617.2 | G63: 2617.2 | H63: 3975 | I63: 13 | J63: =H63*$I63 -> 51675 | L63: =K63*$E63 -> 0 | N63: =M63*$E63 -> 0 | P63: =O63*$E63 -> 0 | Q63: 1950 | R63: =Q63*$E63 -> 1950 | T63: =S63*$E63 -> 0 | U63: 3559 | V63: 1 | W63: =U63*$V63 -> 3559 | Y63: =X63*$E63 -> 0 | AA63: =Z63*$E63 -> 0 | AC63: =AB63*$E63 -> 0 | AE63: =AD63*$E63 -> 0 | AF63: 1651 | AG63: 1 | AH63: =AF63*$AG63 -> 1651 | AJ63: =AI63*$E63 -> 0 | AL63: =AK63*$E63 -> 0 | AN63: =AM63*$E63 -> 0 | AP63: =AO63*$E63 -> 0 | AR63: =AQ63*$E63 -> 0 | AT63: =AS63*$E63 -> 0 | AV63: =AU63*$E63 -> 0 | AX63: =AW63*$E63 -> 0 | AZ63: =AY63*$E63 -> 0 | BB63: =BA63*$E63 -> 0 | BD63: =BC63*$E63 -> 0 | BF63: =BE63*$E63 -> 0 | BH63: =BG63*$E63 -> 0 | BJ63: =BI63*$E63 -> 0 | BL63: =BK63*$E63 -> 0
B64: =IF(ISBLANK($E64)," ",IF(AND(COUNTA(E$59:$E64)+64>72,COUNTA(E$59:$E64)+64<78),CHAR(COUNTA(E$59:$E64)+65),IF(COUNTA(E$59:$E64)+64>77,CHAR(COUNTA(E$59:$E64)+66),CHAR(COUNTA(E$59:$E64)+64)))) -> D | C64: T/BUCI-BU - Bucida Buceras - Black olive tree | D64: No | E64: 9 | F64: 2617.2 | G64: 23554.8 | H64: 4908 | I64: 9 | J64: =H64*$I64 -> 44172 | L64: =K64*$E64 -> 0 | N64: =M64*$E64 -> 0 | P64: =O64*$E64 -> 0 | Q64: 2450 | R64: =Q64*$E64 -> 22050 | T64: =S64*$E64 -> 0 | U64: 3301 | V64: 9 | W64: =U64*$V64 -> 29709 | Y64: =X64*$E64 -> 0 | AA64: =Z64*$E64 -> 0 | AC64: =AB64*$E64 -> 0 | AE64: =AD64*$E64 -> 0 | AF64: 3050 | AG64: 9 | AH64: =AF64*$AG64 -> 27450 | AJ64: =AI64*$E64 -> 0 | AL64: =AK64*$E64 -> 0 | AN64: =AM64*$E64 -> 0 | AP64: =AO64*$E64 -> 0 | AR64: =AQ64*$E64 -> 0 | AT64: =AS64*$E64 -> 0 | AV64: =AU64*$E64 -> 0 | AX64: =AW64*$E64 -> 0 | AZ64: =AY64*$E64 -> 0 | BB64: =BA64*$E64 -> 0 | BD64: =BC64*$E64 -> 0 | BF64: =BE64*$E64 -> 0 | BH64: =BG64*$E64 -> 0 | BJ64: =BI64*$E64 -> 0 | BL64: =BK64*$E64 -> 0
B65: =IF(ISBLANK($E65)," ",IF(AND(COUNTA(E$59:$E65)+64>72,COUNTA(E$59:$E65)+64<78),CHAR(COUNTA(E$59:$E65)+65),IF(COUNTA(E$59:$E65)+64>77,CHAR(COUNTA(E$59:$E65)+66),CHAR(COUNTA(E$59:$E65)+64)))) -> E | C65: T/FICU-RE - Ficus religiosa - Bodhi tree | D65: No | E65: 1 | F65: 4752 | G65: 4752 | H65: 8222 | I65: 1 | J65: =H65*$I65 -> 8222 | L65: =K65*$E65 -> 0 | N65: =M65*$E65 -> 0 | P65: =O65*$E65 -> 0 | Q65: 2900 | R65: =Q65*$E65 -> 2900 | T65: =S65*$E65 -> 0 | U65: 5993 | V65: 1 | W65: =U65*$V65 -> 5993 | Y65: =X65*$E65 -> 0 | AA65: =Z65*$E65 -> 0 | AC65: =AB65*$E65 -> 0 | AE65: =AD65*$E65 -> 0 | AF65: 2023 | AG65: 1 | AH65: =AF65*$AG65 -> 2023 | AJ65: =AI65*$E65 -> 0 | AL65: =AK65*$E65 -> 0 | AN65: =AM65*$E65 -> 0 | AP65: =AO65*$E65 -> 0 | AR65: =AQ65*$E65 -> 0 | AT65: =AS65*$E65 -> 0 | AV65: =AU65*$E65 -> 0 | AX65: =AW65*$E65 -> 0 | AZ65: =AY65*$E65 -> 0 | BB65: =BA65*$E65 -> 0 | BD65: =BC65*$E65 -> 0 | BF65: =BE65*$E65 -> 0 | BH65: =BG65*$E65 -> 0 | BJ65: =BI65*$E65 -> 0 | BL65: =BK65*$E65 -> 0
B66: =IF(ISBLANK($E66)," ",IF(AND(COUNTA(E$59:$E66)+64>72,COUNTA(E$59:$E66)+64<78),CHAR(COUNTA(E$59:$E66)+65),IF(COUNTA(E$59:$E66)+64>77,CHAR(COUNTA(E$59:$E66)+66),CHAR(COUNTA(E$59:$E66)+64)))) -> F | C66: T/FICU-MCN - Ficcus microcarpanitida - Sculptured ficus. | D66: No | E66: 1 | F66: 5260.5 | G66: 5260.5 | H66: 12365 | I66: 1 | J66: =H66*$I66 -> 12365 | L66: =K66*$E66 -> 0 | N66: =M66*$E66 -> 0 | P66: =O66*$E66 -> 0 | Q66: 2720 | R66: =Q66*$E66 -> 2720 | T66: =S66*$E66 -> 0 | U66: 6634 | V66: 1 | W66: =U66*$V66 -> 6634 | Y66: =X66*$E66 -> 0 | AA66: =Z66*$E66 -> 0 | AC66: =AB66*$E66 -> 0 | AE66: =AD66*$E66 -> 0 | AF66: 9063 | AG66: 1 | AH66: =AF66*$AG66 -> 9063 | AJ66: =AI66*$E66 -> 0 | AL66: =AK66*$E66 -> 0 | AN66: =AM66*$E66 -> 0 | AP66: =AO66*$E66 -> 0 | AR66: =AQ66*$E66 -> 0 | AT66: =AS66*$E66 -> 0 | AV66: =AU66*$E66 -> 0 | AX66: =AW66*$E66 -> 0 | AZ66: =AY66*$E66 -> 0 | BB66: =BA66*$E66 -> 0 | BD66: =BC66*$E66 -> 0 | BF66: =BE66*$E66 -> 0 | BH66: =BG66*$E66 -> 0 | BJ66: =BI66*$E66 -> 0 | BL66: =BK66*$E66 -> 0
B67: =IF(ISBLANK($E67)," ",IF(AND(COUNTA(E$59:$E67)+64>72,COUNTA(E$59:$E67)+64<78),CHAR(COUNTA(E$59:$E67)+65),IF(COUNTA(E$59:$E67)+64>77,CHAR(COUNTA(E$59:$E67)+66),CHAR(COUNTA(E$59:$E67)+64)))) -> G | C67: T/PLUM-RU1 - Plumeria rubra acutifolia - Red frangipani tree | D67: No | E67: 7 | F67: 3836.7 | G67: 26856.9 | H67: 7600 | I67: 7 | J67: =H67*$I67 -> 53200 | L67: =K67*$E67 -> 0 | N67: =M67*$E67 -> 0 | P67: =O67*$E67 -> 0 | Q67: 3850 | R67: =Q67*$E67 -> 26950 | T67: =S67*$E67 -> 0 | U67: 4839 | V67: 7 | W67: =U67*$V67 -> 33873 | Y67: =X67*$E67 -> 0 | AA67: =Z67*$E67 -> 0 | AC67: =AB67*$E67 -> 0 | AE67: =AD67*$E67 -> 0 | AF67: 1583 | AG67: 7 | AH67: =AF67*$AG67 -> 11081 | AJ67: =AI67*$E67 -> 0 | AL67: =AK67*$E67 -> 0 | AN67: =AM67*$E67 -> 0 | AP67: =AO67*$E67 -> 0 | AR67: =AQ67*$E67 -> 0 | AT67: =AS67*$E67 -> 0 | AV67: =AU67*$E67 -> 0 | AX67: =AW67*$E67 -> 0 | AZ67: =AY67*$E67 -> 0 | BB67: =BA67*$E67 -> 0 | BD67: =BC67*$E67 -> 0 | BF67: =BE67*$E67 -> 0 | BH67: =BG67*$E67 -> 0 | BJ67: =BI67*$E67 -> 0 | BL67: =BK67*$E67 -> 0
B68: =IF(ISBLANK($E68)," ",IF(AND(COUNTA(E$59:$E68)+64>72,COUNTA(E$59:$E68)+64<78),CHAR(COUNTA(E$59:$E68)+65),IF(COUNTA(E$59:$E68)+64>77,CHAR(COUNTA(E$59:$E68)+66),CHAR(COUNTA(E$59:$E68)+64)))) -> H | C68: T/PLUM-RU2 - Plumeria rubra acutifolia - Red frangipani tree | D68: No | E68: 1 | F68: 7292.7 | G68: 7292.7 | H68: 12365 | I68: 1 | J68: =H68*$I68 -> 12365 | L68: =K68*$E68 -> 0 | N68: =M68*$E68 -> 0 | P68: =O68*$E68 -> 0 | Q68: 3950 | R68: =Q68*$E68 -> 3950 | T68: =S68*$E68 -> 0 | U68: 9198 | V68: 1 | W68: =U68*$V68 -> 9198 | Y68: =X68*$E68 -> 0 | AA68: =Z68*$E68 -> 0 | AC68: =AB68*$E68 -> 0 | AE68: =AD68*$E68 -> 0 | AF68: 2023 | AG68: 1 | AH68: =AF68*$AG68 -> 2023 | AJ68: =AI68*$E68 -> 0 | AL68: =AK68*$E68 -> 0 | AN68: =AM68*$E68 -> 0 | AP68: =AO68*$E68 -> 0 | AR68: =AQ68*$E68 -> 0 | AT68: =AS68*$E68 -> 0 | AV68: =AU68*$E68 -> 0 | AX68: =AW68*$E68 -> 0 | AZ68: =AY68*$E68 -> 0 | BB68: =BA68*$E68 -> 0 | BD68: =BC68*$E68 -> 0 | BF68: =BE68*$E68 -> 0 | BH68: =BG68*$E68 -> 0 | BJ68: =BI68*$E68 -> 0 | BL68: =BK68*$E68 -> 0
B69: =IF(ISBLANK($E69)," ",IF(AND(COUNTA(E$59:$E69)+64>72,COUNTA(E$59:$E69)+64<78),CHAR(COUNTA(E$59:$E69)+65),IF(COUNTA(E$59:$E69)+64>77,CHAR(COUNTA(E$59:$E69)+66),CHAR(COUNTA(E$59:$E69)+64)))) -> J | C69: T/VITE-AC - Vitex agnus castus - Chaste tree | D69: No | E69: 8 | F69: 1397.7 | G69: 11181.6 | H69: 2940 | I69: 8 | J69: =H69*$I69 -> 23520 | L69: =K69*$E69 -> 0 | N69: =M69*$E69 -> 0 | P69: =O69*$E69 -> 0 | Q69: 2150 | R69: =Q69*$E69 -> 17200 | T69: =S69*$E69 -> 0 | U69: 1762 | V69: 8 | W69: =U69*$V69 -> 14096 | Y69: =X69*$E69 -> 0 | AA69: =Z69*$E69 -> 0 | AC69: =AB69*$E69 -> 0 | AE69: =AD69*$E69 -> 0 | AF69: 1143 | AG69: 8 | AH69: =AF69*$AG69 -> 9144 | AJ69: =AI69*$E69 -> 0 | AL69: =AK69*$E69 -> 0 | AN69: =AM69*$E69 -> 0 | AP69: =AO69*$E69 -> 0 | AR69: =AQ69*$E69 -> 0 | AT69: =AS69*$E69 -> 0 | AV69: =AU69*$E69 -> 0 | AX69: =AW69*$E69 -> 0 | AZ69: =AY69*$E69 -> 0 | BB69: =BA69*$E69 -> 0 | BD69: =BC69*$E69 -> 0 | BF69: =BE69*$E69 -> 0 | BH69: =BG69*$E69 -> 0 | BJ69: =BI69*$E69 -> 0 | BL69: =BK69*$E69 -> 0
B70: =IF(ISBLANK($E70)," ",IF(AND(COUNTA(E$59:$E70)+64>72,COUNTA(E$59:$E70)+64<78),CHAR(COUNTA(E$59:$E70)+65),IF(COUNTA(E$59:$E70)+64>77,CHAR(COUNTA(E$59:$E70)+66),CHAR(COUNTA(E$59:$E70)+64)))) -> K | C70: T/CALL-LA - Callistemon lanceolatus - Weeping bottle brush | D70: No | E70: 4 | F70: 2007.9 | G70: 8031.6 | H70: 3458 | I70: 4 | J70: =H70*$I70 -> 13832 | L70: =K70*$E70 -> 0 | N70: =M70*$E70 -> 0 | P70: =O70*$E70 -> 0 | Q70: 2400 | R70: =Q70*$E70 -> 9600 | T70: =S70*$E70 -> 0 | U70: 2532 | V70: 4 | W70: =U70*$V70 -> 10128 | Y70: =X70*$E70 -> 0 | AA70: =Z70*$E70 -> 0 | AC70: =AB70*$E70 -> 0 | AE70: =AD70*$E70 -> 0 | AF70: 1656 | AG70: 4 | AH70: =AF70*$AG70 -> 6624 | AJ70: =AI70*$E70 -> 0 | AL70: =AK70*$E70 -> 0 | AN70: =AM70*$E70 -> 0 | AP70: =AO70*$E70 -> 0 | AR70: =AQ70*$E70 -> 0 | AT70: =AS70*$E70 -> 0 | AV70: =AU70*$E70 -> 0 | AX70: =AW70*$E70 -> 0 | AZ70: =AY70*$E70 -> 0 | BB70: =BA70*$E70 -> 0 | BD70: =BC70*$E70 -> 0 | BF70: =BE70*$E70 -> 0 | BH70: =BG70*$E70 -> 0 | BJ70: =BI70*$E70 -> 0 | BL70: =BK70*$E70 -> 0
B71: =IF(ISBLANK($E71)," ",IF(AND(COUNTA(E$59:$E71)+64>72,COUNTA(E$59:$E71)+64<78),CHAR(COUNTA(E$59:$E71)+65),IF(COUNTA(E$59:$E71)+64>77,CHAR(COUNTA(E$59:$E71)+66),CHAR(COUNTA(E$59:$E71)+64)))) -> L | C71: T/HIBI-TRU - Hibiscus filaceus rubra | D71: No | E71: 1 | F71: 1804.5 | G71: 1804.5 | H71: 6150 | I71: 1 | J71: =H71*$I71 -> 6150 | L71: =K71*$E71 -> 0 | N71: =M71*$E71 -> 0 | P71: =O71*$E71 -> 0 | Q71: 2250 | R71: =Q71*$E71 -> 2250 | T71: =S71*$E71 -> 0 | U71: 2275 | V71: 1 | W71: =U71*$V71 -> 2275 | Y71: =X71*$E71 -> 0 | AA71: =Z71*$E71 -> 0 | AC71: =AB71*$E71 -> 0 | AE71: =AD71*$E71 -> 0 | AF71: 2023 | AG71: 1 | AH71: =AF71*$AG71 -> 2023 | AJ71: =AI71*$E71 -> 0 | AL71: =AK71*$E71 -> 0 | AN71: =AM71*$E71 -> 0 | AP71: =AO71*$E71 -> 0 | AR71: =AQ71*$E71 -> 0 | AT71: =AS71*$E71 -> 0 | AV71: =AU71*$E71 -> 0 | AX71: =AW71*$E71 -> 0 | AZ71: =AY71*$E71 -> 0 | BB71: =BA71*$E71 -> 0 | BD71: =BC71*$E71 -> 0 | BF71: =BE71*$E71 -> 0 | BH71: =BG71*$E71 -> 0 | BJ71: =BI71*$E71 -> 0 | BL71: =BK71*$E71 -> 0
B72: =IF(ISBLANK($E72)," ",IF(AND(COUNTA(E$59:$E72)+64>72,COUNTA(E$59:$E72)+64<78),CHAR(COUNTA(E$59:$E72)+65),IF(COUNTA(E$59:$E72)+64>77,CHAR(COUNTA(E$59:$E72)+66),CHAR(COUNTA(E$59:$E72)+64)))) | C72: Palms
B73: =IF(ISBLANK($E73)," ",IF(AND(COUNTA(E$59:$E73)+64>72,COUNTA(E$59:$E73)+64<78),CHAR(COUNTA(E$59:$E73)+65),IF(COUNTA(E$59:$E73)+64>77,CHAR(COUNTA(E$59:$E73)+66),CHAR(COUNTA(E$59:$E73)+64)))) -> M | C73: P/WODY-BI - Wodyetia bifurcata - Foxtail palm. | D73: No | E73: 8 | F73: 6073.2 | G73: 48585.6 | H73: 18384 | I73: 8 | J73: =H73*$I73 -> 147072 | L73: =K73*$E73 -> 0 | N73: =M73*$E73 -> 0 | P73: =O73*$E73 -> 0 | Q73: 4300 | R73: =Q73*$E73 -> 34400 | T73: =S73*$E73 -> 0 | U73: 7659 | V73: 8 | W73: =U73*$V73 -> 61272 | Y73: =X73*$E73 -> 0 | AA73: =Z73*$E73 -> 0 | AC73: =AB73*$E73 -> 0 | AE73: =AD73*$E73 -> 0 | AF73: 8854 | AG73: 8 | AH73: =AF73*$AG73 -> 70832 | AJ73: =AI73*$E73 -> 0 | AL73: =AK73*$E73 -> 0 | AN73: =AM73*$E73 -> 0 | AP73: =AO73*$E73 -> 0 | AR73: =AQ73*$E73 -> 0 | AT73: =AS73*$E73 -> 0 | AV73: =AU73*$E73 -> 0 | AX73: =AW73*$E73 -> 0 | AZ73: =AY73*$E73 -> 0 | BB73: =BA73*$E73 -> 0 | BD73: =BC73*$E73 -> 0 | BF73: =BE73*$E73 -> 0 | BH73: =BG73*$E73 -> 0 | BJ73: =BI73*$E73 -> 0 | BL73: =BK73*$E73 -> 0
B74: =IF(ISBLANK($E74)," ",IF(AND(COUNTA(E$59:$E74)+64>72,COUNTA(E$59:$E74)+64<78),CHAR(COUNTA(E$59:$E74)+65),IF(COUNTA(E$59:$E74)+64>77,CHAR(COUNTA(E$59:$E74)+66),CHAR(COUNTA(E$59:$E74)+64)))) | C74: Accent Plant
B75: =IF(ISBLANK($E75)," ",IF(AND(COUNTA(E$59:$E75)+64>72,COUNTA(E$59:$E75)+64<78),CHAR(COUNTA(E$59:$E75)+65),IF(COUNTA(E$59:$E75)+64>77,CHAR(COUNTA(E$59:$E75)+66),CHAR(COUNTA(E$59:$E75)+64)))) -> N | C75: AP/SPAT-WA - Spathiphyllum wallisii - Giant Spatiphyllum. | D75: No | E75: 12 | F75: 179.1 | G75: 2149.2 | H75: 386 | I75: 12 | J75: =H75*$I75 -> 4632 | L75: =K75*$E75 -> 0 | N75: =M75*$E75 -> 0 | P75: =O75*$E75 -> 0 | Q75: 950 | R75: =Q75*$E75 -> 11400 | T75: =S75*$E75 -> 0 | U75: 225 | V75: 12 | W75: =U75*$V75 -> 2700 | Y75: =X75*$E75 -> 0 | AA75: =Z75*$E75 -> 0 | AC75: =AB75*$E75 -> 0 | AE75: =AD75*$E75 -> 0 | AF75: 527 | AG75: 12 | AH75: =AF75*$AG75 -> 6324 | AJ75: =AI75*$E75 -> 0 | AL75: =AK75*$E75 -> 0 | AN75: =AM75*$E75 -> 0 | AP75: =AO75*$E75 -> 0 | AR75: =AQ75*$E75 -> 0 | AT75: =AS75*$E75 -> 0 | AV75: =AU75*$E75 -> 0 | AX75: =AW75*$E75 -> 0 | AZ75: =AY75*$E75 -> 0 | BB75: =BA75*$E75 -> 0 | BD75: =BC75*$E75 -> 0 | BF75: =BE75*$E75 -> 0 | BH75: =BG75*$E75 -> 0 | BJ75: =BI75*$E75 -> 0 | BL75: =BK75*$E75 -> 0
B76: =IF(ISBLANK($E76)," ",IF(AND(COUNTA(E$59:$E76)+64>72,COUNTA(E$59:$E76)+64<78),CHAR(COUNTA(E$59:$E76)+65),IF(COUNTA(E$59:$E76)+64>77,CHAR(COUNTA(E$59:$E76)+66),CHAR(COUNTA(E$59:$E76)+64)))) -> P | C76: AP/RAPH-EX - Raphix excelsa - Lady palm | D76: No | E76: 7 | F76: 260.1 | G76: 1820.7 | H76: 500 | I76: 7 | J76: =H76*$I76 -> 3500 | L76: =K76*$E76 -> 0 | N76: =M76*$E76 -> 0 | P76: =O76*$E76 -> 0 | Q76: 1150 | R76: =Q76*$E76 -> 8050 | T76: =S76*$E76 -> 0 | U76: 327 | V76: 7 | W76: =U76*$V76 -> 2289 | Y76: =X76*$E76 -> 0 | AA76: =Z76*$E76 -> 0 | AC76: =AB76*$E76 -> 0 | AE76: =AD76*$E76 -> 0 | AF76: 527 | AG76: 7 | AH76: =AF76*$AG76 -> 3689 | AJ76: =AI76*$E76 -> 0 | AL76: =AK76*$E76 -> 0 | AN76: =AM76*$E76 -> 0 | AP76: =AO76*$E76 -> 0 | AR76: =AQ76*$E76 -> 0 | AT76: =AS76*$E76 -> 0 | AV76: =AU76*$E76 -> 0 | AX76: =AW76*$E76 -> 0 | AZ76: =AY76*$E76 -> 0 | BB76: =BA76*$E76 -> 0 | BD76: =BC76*$E76 -> 0 | BF76: =BE76*$E76 -> 0 | BH76: =BG76*$E76 -> 0 | BJ76: =BI76*$E76 -> 0 | BL76: =BK76*$E76 -> 0
B77: =IF(ISBLANK($E77)," ",IF(AND(COUNTA(E$59:$E77)+64>72,COUNTA(E$59:$E77)+64<78),CHAR(COUNTA(E$59:$E77)+65),IF(COUNTA(E$59:$E77)+64>77,CHAR(COUNTA(E$59:$E77)+66),CHAR(COUNTA(E$59:$E77)+64)))) -> Q | C77: AP/SANS-TR - Sansevieria trifasciata - Snake plant | D77: No | E77: 9 | F77: 90 | G77: 810 | H77: 116 | I77: 9 | J77: =H77*$I77 -> 1044 | L77: =K77*$E77 -> 0 | N77: =M77*$E77 -> 0 | P77: =O77*$E77 -> 0 | Q77: 140 | R77: =Q77*$E77 -> 1260 | T77: =S77*$E77 -> 0 | U77: 113 | V77: 9 | W77: =U77*$V77 -> 1017 | Y77: =X77*$E77 -> 0 | AA77: =Z77*$E77 -> 0 | AC77: =AB77*$E77 -> 0 | AE77: =AD77*$E77 -> 0 | AF77: 425 | AG77: 9 | AH77: =AF77*$AG77 -> 3825 | AJ77: =AI77*$E77 -> 0 | AL77: =AK77*$E77 -> 0 | AN77: =AM77*$E77 -> 0 | AP77: =AO77*$E77 -> 0 | AR77: =AQ77*$E77 -> 0 | AT77: =AS77*$E77 -> 0 | AV77: =AU77*$E77 -> 0 | AX77: =AW77*$E77 -> 0 | AZ77: =AY77*$E77 -> 0 | BB77: =BA77*$E77 -> 0 | BD77: =BC77*$E77 -> 0 | BF77: =BE77*$E77 -> 0 | BH77: =BG77*$E77 -> 0 | BJ77: =BI77*$E77 -> 0 | BL77: =BK77*$E77 -> 0
B78: =IF(ISBLANK($E78)," ",IF(AND(COUNTA(E$59:$E78)+64>72,COUNTA(E$59:$E78)+64<78),CHAR(COUNTA(E$59:$E78)+65),IF(COUNTA(E$59:$E78)+64>77,CHAR(COUNTA(E$59:$E78)+66),CHAR(COUNTA(E$59:$E78)+64)))) -> R | C78: AR/BAMB - Artificial Bamboo | D78: No | E78: 6 | F78: 6692.4 | G78: 40154.4 | H78: 529 | I78: 6 | J78: =H78*$I78 -> 3174 | L78: =K78*$E78 -> 0 | N78: =M78*$E78 -> 0 | P78: =O78*$E78 -> 0 | Q78: 240 | R78: =Q78*$E78 -> 1440 | T78: =S78*$E78 -> 0 | U78: 8441 | V78: 6 | W78: =U78*$V78 -> 50646 | Y78: =X78*$E78 -> 0 | AA78: =Z78*$E78 -> 0 | AC78: =AB78*$E78 -> 0 | AE78: =AD78*$E78 -> 0 | AG78: 6 | AH78: =AF78*$AG78 -> 0 | AJ78: =AI78*$E78 -> 0 | AL78: =AK78*$E78 -> 0 | AN78: =AM78*$E78 -> 0 | AP78: =AO78*$E78 -> 0 | AR78: =AQ78*$E78 -> 0 | AT78: =AS78*$E78 -> 0 | AV78: =AU78*$E78 -> 0 | AX78: =AW78*$E78 -> 0 | AZ78: =AY78*$E78 -> 0 | BB78: =BA78*$E78 -> 0 | BD78: =BC78*$E78 -> 0 | BF78: =BE78*$E78 -> 0 | BH78: =BG78*$E78 -> 0 | BJ78: =BI78*$E78 -> 0 | BL78: =BK78*$E78 -> 0
B79: =IF(ISBLANK($E79)," ",IF(AND(COUNTA(E$59:$E79)+64>72,COUNTA(E$59:$E79)+64<78),CHAR(COUNTA(E$59:$E79)+65),IF(COUNTA(E$59:$E79)+64>77,CHAR(COUNTA(E$59:$E79)+66),CHAR(COUNTA(E$59:$E79)+64)))) -> S | C79: AP/MURR-PA - Murraya paniculata - Orange jasmine | D79: No | E79: 8 | F79: 68.4 | G79: 684 | H79: 593 | I79: 8 | J79: =H79*$I79 -> 4744 | L79: =K79*$E79 -> 0 | N79: =M79*$E79 -> 0 | P79: =O79*$E79 -> 0 | Q79: 120 | R79: =Q79*$E79 -> 960 | T79: =S79*$E79 -> 0 | U79: 86 | V79: 10 | W79: =U79*$V79 -> 860 | Y79: =X79*$E79 -> 0 | AA79: =Z79*$E79 -> 0 | AC79: =AB79*$E79 -> 0 | AE79: =AD79*$E79 -> 0 | AF79: 1187 | AG79: 8 | AH79: =AF79*$AG79 -> 9496 | AJ79: =AI79*$E79 -> 0 | AL79: =AK79*$E79 -> 0 | AN79: =AM79*$E79 -> 0 | AP79: =AO79*$E79 -> 0 | AR79: =AQ79*$E79 -> 0 | AT79: =AS79*$E79 -> 0 | AV79: =AU79*$E79 -> 0 | AX79: =AW79*$E79 -> 0 | AZ79: =AY79*$E79 -> 0 | BB79: =BA79*$E79 -> 0 | BD79: =BC79*$E79 -> 0 | BF79: =BE79*$E79 -> 0 | BH79: =BG79*$E79 -> 0 | BJ79: =BI79*$E79 -> 0 | BL79: =BK79*$E79 -> 0
B80: =IF(ISBLANK($E80)," ",IF(AND(COUNTA(E$59:$E80)+64>72,COUNTA(E$59:$E80)+64<78),CHAR(COUNTA(E$59:$E80)+65),IF(COUNTA(E$59:$E80)+64>77,CHAR(COUNTA(E$59:$E80)+66),CHAR(COUNTA(E$59:$E80)+64)))) -> T | C80: AP/CHAM-HU - Chamaeropes humilis - Mediterranean palm | D80: No | E80: 9 | F80: 1397.7 | G80: 12579.3 | H80: 1865 | I80: 9 | J80: =H80*$I80 -> 16785 | L80: =K80*$E80 -> 0 | N80: =M80*$E80 -> 0 | P80: =O80*$E80 -> 0 | Q80: 480 | R80: =Q80*$E80 -> 4320 | T80: =S80*$E80 -> 0 | U80: 1762 | V80: 9 | W80: =U80*$V80 -> 15858 | Y80: =X80*$E80 -> 0 | AA80: =Z80*$E80 -> 0 | AC80: =AB80*$E80 -> 0 | AE80: =AD80*$E80 -> 0 | AF80: 3241 | AG80: 9 | AH80: =AF80*$AG80 -> 29169 | AJ80: =AI80*$E80 -> 0 | AL80: =AK80*$E80 -> 0 | AN80: =AM80*$E80 -> 0 | AP80: =AO80*$E80 -> 0 | AR80: =AQ80*$E80 -> 0 | AT80: =AS80*$E80 -> 0 | AV80: =AU80*$E80 -> 0 | AX80: =AW80*$E80 -> 0 | AZ80: =AY80*$E80 -> 0 | BB80: =BA80*$E80 -> 0 | BD80: =BC80*$E80 -> 0 | BF80: =BE80*$E80 -> 0 | BH80: =BG80*$E80 -> 0 | BJ80: =BI80*$E80 -> 0 | BL80: =BK80*$E80 -> 0
B81: =IF(ISBLANK($E81)," ",IF(AND(COUNTA(E$59:$E81)+64>72,COUNTA(E$59:$E81)+64<78),CHAR(COUNTA(E$59:$E81)+65),IF(COUNTA(E$59:$E81)+64>77,CHAR(COUNTA(E$59:$E81)+66),CHAR(COUNTA(E$59:$E81)+64)))) -> U | C81: AP/VITE-RO - Vitexrotundifolia - Beach vitex | D81: No | E81: 78 | F81: 137.7 | G81: 10740.6 | H81: 129 | I81: 78 | J81: =H81*$I81 -> 10062 | L81: =K81*$E81 -> 0 | N81: =M81*$E81 -> 0 | P81: =O81*$E81 -> 0 | Q81: 64 | R81: =Q81*$E81 -> 4992 | T81: =S81*$E81 -> 0 | U81: 173 | V81: 78 | W81: =U81*$V81 -> 13494 | Y81: =X81*$E81 -> 0 | AA81: =Z81*$E81 -> 0 | AC81: =AB81*$E81 -> 0 | AE81: =AD81*$E81 -> 0 | AF81: 351 | AG81: 78 | AH81: =AF81*$AG81 -> 27378 | AJ81: =AI81*$E81 -> 0 | AL81: =AK81*$E81 -> 0 | AN81: =AM81*$E81 -> 0 | AP81: =AO81*$E81 -> 0 | AR81: =AQ81*$E81 -> 0 | AT81: =AS81*$E81 -> 0 | AV81: =AU81*$E81 -> 0 | AX81: =AW81*$E81 -> 0 | AZ81: =AY81*$E81 -> 0 | BB81: =BA81*$E81 -> 0 | BD81: =BC81*$E81 -> 0 | BF81: =BE81*$E81 -> 0 | BH81: =BG81*$E81 -> 0 | BJ81: =BI81*$E81 -> 0 | BL81: =BK81*$E81 -> 0
B82: =IF(ISBLANK($E82)," ",IF(AND(COUNTA(E$59:$E82)+64>72,COUNTA(E$59:$E82)+64<78),CHAR(COUNTA(E$59:$E82)+65),IF(COUNTA(E$59:$E82)+64>77,CHAR(COUNTA(E$59:$E82)+66),CHAR(COUNTA(E$59:$E82)+64)))) -> V | C82: AP/PENN-SE - Pennisetumsetaceum - Fountain grass | D82: No | E82: 21 | F82: 33.3 | G82: 699.3 | H82: 96 | I82: 21 | J82: =H82*$I82 -> 2016 | L82: =K82*$E82 -> 0 | N82: =M82*$E82 -> 0 | P82: =O82*$E82 -> 0 | Q82: 34 | R82: =Q82*$E82 -> 714 | T82: =S82*$E82 -> 0 | U82: 42 | V82: 21 | W82: =U82*$V82 -> 882 | Y82: =X82*$E82 -> 0 | AA82: =Z82*$E82 -> 0 | AC82: =AB82*$E82 -> 0 | AE82: =AD82*$E82 -> 0 | AF82: 344 | AG82: 21 | AH82: =AF82*$AG82 -> 7224 | AJ82: =AI82*$E82 -> 0 | AL82: =AK82*$E82 -> 0 | AN82: =AM82*$E82 -> 0 | AP82: =AO82*$E82 -> 0 | AR82: =AQ82*$E82 -> 0 | AT82: =AS82*$E82 -> 0 | AV82: =AU82*$E82 -> 0 | AX82: =AW82*$E82 -> 0 | AZ82: =AY82*$E82 -> 0 | BB82: =BA82*$E82 -> 0 | BD82: =BC82*$E82 -> 0 | BF82: =BE82*$E82 -> 0 | BH82: =BG82*$E82 -> 0 | BJ82: =BI82*$E82 -> 0 | BL82: =BK82*$E82 -> 0
B83: =IF(ISBLANK($E83)," ",IF(AND(COUNTA(E$59:$E83)+64>72,COUNTA(E$59:$E83)+64<78),CHAR(COUNTA(E$59:$E83)+65),IF(COUNTA(E$59:$E83)+64>77,CHAR(COUNTA(E$59:$E83)+66),CHAR(COUNTA(E$59:$E83)+64)))) -> W | C83: T/OLIV-EU - Olivera europa - Olive tree | D83: No | E83: 2 | F83: 5260.5 | G83: 10521 | H83: 25018 | I83: 2 | J83: =H83*$I83 -> 50036 | L83: =K83*$E83 -> 0 | N83: =M83*$E83 -> 0 | P83: =O83*$E83 -> 0 | Q83: 12500 | R83: =Q83*$E83 -> 25000 | T83: =S83*$E83 -> 0 | U83: 6634 | V83: 2 | W83: =U83*$V83 -> 13268 | Y83: =X83*$E83 -> 0 | AA83: =Z83*$E83 -> 0 | AC83: =AB83*$E83 -> 0 | AE83: =AD83*$E83 -> 0 | AF83: 3974 | AG83: 2 | AH83: =AF83*$AG83 -> 7948 | AJ83: =AI83*$E83 -> 0 | AL83: =AK83*$E83 -> 0 | AN83: =AM83*$E83 -> 0 | AP83: =AO83*$E83 -> 0 | AR83: =AQ83*$E83 -> 0 | AT83: =AS83*$E83 -> 0 | AV83: =AU83*$E83 -> 0 | AX83: =AW83*$E83 -> 0 | AZ83: =AY83*$E83 -> 0 | BB83: =BA83*$E83 -> 0 | BD83: =BC83*$E83 -> 0 | BF83: =BE83*$E83 -> 0 | BH83: =BG83*$E83 -> 0 | BJ83: =BI83*$E83 -> 0 | BL83: =BK83*$E83 -> 0
B84: =IF(ISBLANK($E84)," ",IF(AND(COUNTA(E$59:$E84)+64>72,COUNTA(E$59:$E84)+64<78),CHAR(COUNTA(E$59:$E84)+65),IF(COUNTA(E$59:$E84)+64>77,CHAR(COUNTA(E$59:$E84)+66),CHAR(COUNTA(E$59:$E84)+64)))) | C84: Ground Cover
B85: =IF(ISBLANK($E85)," ",IF(AND(COUNTA(E$83:$E85)+64>72,COUNTA(E$83:$E85)+64<78),CHAR(COUNTA(E$83:$E85)+65),IF(COUNTA(E$83:$E85)+64>77,CHAR(COUNTA(E$83:$E85)+66),CHAR(COUNTA(E$83:$E85)+64)))) -> B | C85: GC/ASPA-DS - Asparagus densiflorus spengeri - Asparagus fern. | D85: No | E85: 133 | F85: 14.4 | G85: 1915.2 | H85: 49 | I85: 133 | J85: =H85*$I85 -> 6517 | L85: =K85*$E85 -> 0 | N85: =M85*$E85 -> 0 | P85: =O85*$E85 -> 0 | Q85: 38 | R85: =Q85*$E85 -> 5054 | T85: =S85*$E85 -> 0 | U85: 18 | V85: 133 | W85: =U85*$V85 -> 2394 | Y85: =X85*$E85 -> 0 | AA85: =Z85*$E85 -> 0 | AC85: =AB85*$E85 -> 0 | AE85: =AD85*$E85 -> 0 | AF85: 32 | AG85: 133 | AH85: =AF85*$AG85 -> 4256 | AJ85: =AI85*$E85 -> 0 | AL85: =AK85*$E85 -> 0 | AN85: =AM85*$E85 -> 0 | AP85: =AO85*$E85 -> 0 | AR85: =AQ85*$E85 -> 0 | AT85: =AS85*$E85 -> 0 | AV85: =AU85*$E85 -> 0 | AX85: =AW85*$E85 -> 0 | AZ85: =AY85*$E85 -> 0 | BB85: =BA85*$E85 -> 0 | BD85: =BC85*$E85 -> 0 | BF85: =BE85*$E85 -> 0 | BH85: =BG85*$E85 -> 0 | BJ85: =BI85*$E85 -> 0 | BL85: =BK85*$E85 -> 0
B86: =IF(ISBLANK($E86)," ",IF(AND(COUNTA(E$83:$E86)+64>72,COUNTA(E$83:$E86)+64<78),CHAR(COUNTA(E$83:$E86)+65),IF(COUNTA(E$83:$E86)+64>77,CHAR(COUNTA(E$83:$E86)+66),CHAR(COUNTA(E$83:$E86)+64)))) -> C | C86: GC/YUCC-DE - Yucca desmetiana - Dwarf yucca | D86: No | E86: 203 | F86: 46.8 | G86: 9500.4 | H86: 161 | I86: 203 | J86: =H86*$I86 -> 32683 | L86: =K86*$E86 -> 0 | N86: =M86*$E86 -> 0 | P86: =O86*$E86 -> 0 | Q86: 132 | R86: =Q86*$E86 -> 26796 | T86: =S86*$E86 -> 0 | U86: 58 | V86: 203 | W86: =U86*$V86 -> 11774 | Y86: =X86*$E86 -> 0 | AA86: =Z86*$E86 -> 0 | AC86: =AB86*$E86 -> 0 | AE86: =AD86*$E86 -> 0 | AF86: 40 | AG86: 203 | AH86: =AF86*$AG86 -> 8120 | AJ86: =AI86*$E86 -> 0 | AL86: =AK86*$E86 -> 0 | AN86: =AM86*$E86 -> 0 | AP86: =AO86*$E86 -> 0 | AR86: =AQ86*$E86 -> 0 | AT86: =AS86*$E86 -> 0 | AV86: =AU86*$E86 -> 0 | AX86: =AW86*$E86 -> 0 | AZ86: =AY86*$E86 -> 0 | BB86: =BA86*$E86 -> 0 | BD86: =BC86*$E86 -> 0 | BF86: =BE86*$E86 -> 0 | BH86: =BG86*$E86 -> 0 | BJ86: =BI86*$E86 -> 0 | BL86: =BK86*$E86 -> 0
B87: =IF(ISBLANK($E87)," ",IF(AND(COUNTA(E$83:$E87)+64>72,COUNTA(E$83:$E87)+64<78),CHAR(COUNTA(E$83:$E87)+65),IF(COUNTA(E$83:$E87)+64>77,CHAR(COUNTA(E$83:$E87)+66),CHAR(COUNTA(E$83:$E87)+64)))) -> D | C87: GC/VITE-RO - Vitexrotundifolia - Beach vitex | D87: No | E87: 299 | F87: 15.3 | G87: 4574.7 | H87: 53 | I87: 299 | J87: =H87*$I87 -> 15847 | L87: =K87*$E87 -> 0 | N87: =M87*$E87 -> 0 | P87: =O87*$E87 -> 0 | Q87: 74 | R87: =Q87*$E87 -> 22126 | T87: =S87*$E87 -> 0 | U87: 19 | V87: 299 | W87: =U87*$V87 -> 5681 | Y87: =X87*$E87 -> 0 | AA87: =Z87*$E87 -> 0 | AC87: =AB87*$E87 -> 0 | AE87: =AD87*$E87 -> 0 | AF87: 54 | AG87: 299 | AH87: =AF87*$AG87 -> 16146 | AJ87: =AI87*$E87 -> 0 | AL87: =AK87*$E87 -> 0 | AN87: =AM87*$E87 -> 0 | AP87: =AO87*$E87 -> 0 | AR87: =AQ87*$E87 -> 0 | AT87: =AS87*$E87 -> 0 | AV87: =AU87*$E87 -> 0 | AX87: =AW87*$E87 -> 0 | AZ87: =AY87*$E87 -> 0 | BB87: =BA87*$E87 -> 0 | BD87: =BC87*$E87 -> 0 | BF87: =BE87*$E87 -> 0 | BH87: =BG87*$E87 -> 0 | BJ87: =BI87*$E87 -> 0 | BL87: =BK87*$E87 -> 0
B88: =IF(ISBLANK($E88)," ",IF(AND(COUNTA(E$83:$E88)+64>72,COUNTA(E$83:$E88)+64<78),CHAR(COUNTA(E$83:$E88)+65),IF(COUNTA(E$83:$E88)+64>77,CHAR(COUNTA(E$83:$E88)+66),CHAR(COUNTA(E$83:$E88)+64)))) -> E | C88: GC/ASYS-GA - Asystasia gangetica - Chinese violet | D88: No | E88: 879 | F88: 7.2 | G88: 6328.8 | H88: 41 | I88: 879 | J88: =H88*$I88 -> 36039 | L88: =K88*$E88 -> 0 | N88: =M88*$E88 -> 0 | P88: =O88*$E88 -> 0 | Q88: 42 | R88: =Q88*$E88 -> 36918 | T88: =S88*$E88 -> 0 | U88: 9 | V88: 949 | W88: =U88*$V88 -> 8541 | Y88: =X88*$E88 -> 0 | AA88: =Z88*$E88 -> 0 | AC88: =AB88*$E88 -> 0 | AE88: =AD88*$E88 -> 0 | AF88: 25 | AG88: 879 | AH88: =AF88*$AG88 -> 21975 | AJ88: =AI88*$E88 -> 0 | AL88: =AK88*$E88 -> 0 | AN88: =AM88*$E88 -> 0 | AP88: =AO88*$E88 -> 0 | AR88: =AQ88*$E88 -> 0 | AT88: =AS88*$E88 -> 0 | AV88: =AU88*$E88 -> 0 | AX88: =AW88*$E88 -> 0 | AZ88: =AY88*$E88 -> 0 | BB88: =BA88*$E88 -> 0 | BD88: =BC88*$E88 -> 0 | BF88: =BE88*$E88 -> 0 | BH88: =BG88*$E88 -> 0 | BJ88: =BI88*$E88 -> 0 | BL88: =BK88*$E88 -> 0
B89: =IF(ISBLANK($E89)," ",IF(AND(COUNTA(E$83:$E89)+64>72,COUNTA(E$83:$E89)+64<78),CHAR(COUNTA(E$83:$E89)+65),IF(COUNTA(E$83:$E89)+64>77,CHAR(COUNTA(E$83:$E89)+66),CHAR(COUNTA(E$83:$E89)+64)))) -> F | C89: GC/IRES-LI - Iresine lindenii - Blood leaf plant | D89: No | E89: 656 | F89: 9 | G89: 5904 | H89: 41 | I89: 656 | J89: =H89*$I89 -> 26896 | L89: =K89*$E89 -> 0 | N89: =M89*$E89 -> 0 | P89: =O89*$E89 -> 0 | Q89: 38 | R89: =Q89*$E89 -> 24928 | T89: =S89*$E89 -> 0 | U89: 11 | V89: 656 | W89: =U89*$V89 -> 7216 | Y89: =X89*$E89 -> 0 | AA89: =Z89*$E89 -> 0 | AC89: =AB89*$E89 -> 0 | AE89: =AD89*$E89 -> 0 | AF89: 32 | AG89: 656 | AH89: =AF89*$AG89 -> 20992 | AJ89: =AI89*$E89 -> 0 | AL89: =AK89*$E89 -> 0 | AN89: =AM89*$E89 -> 0 | AP89: =AO89*$E89 -> 0 | AR89: =AQ89*$E89 -> 0 | AT89: =AS89*$E89 -> 0 | AV89: =AU89*$E89 -> 0 | AX89: =AW89*$E89 -> 0 | AZ89: =AY89*$E89 -> 0 | BB89: =BA89*$E89 -> 0 | BD89: =BC89*$E89 -> 0 | BF89: =BE89*$E89 -> 0 | BH89: =BG89*$E89 -> 0 | BJ89: =BI89*$E89 -> 0 | BL89: =BK89*$E89 -> 0
B90: =IF(ISBLANK($E90)," ",IF(AND(COUNTA(E$83:$E90)+64>72,COUNTA(E$83:$E90)+64<78),CHAR(COUNTA(E$83:$E90)+65),IF(COUNTA(E$83:$E90)+64>77,CHAR(COUNTA(E$83:$E90)+66),CHAR(COUNTA(E$83:$E90)+64)))) -> G | C90: GC/ATRI-SE - Atriplex sembibaccata - Atriplex | D90: No | E90: 211 | F90: 10.8 | G90: 2278.8 | H90: 47 | I90: 211 | J90: =H90*$I90 -> 9917 | L90: =K90*$E90 -> 0 | N90: =M90*$E90 -> 0 | P90: =O90*$E90 -> 0 | Q90: 44 | R90: =Q90*$E90 -> 9284 | T90: =S90*$E90 -> 0 | U90: 13 | V90: 211 | W90: =U90*$V90 -> 2743 | Y90: =X90*$E90 -> 0 | AA90: =Z90*$E90 -> 0 | AC90: =AB90*$E90 -> 0 | AE90: =AD90*$E90 -> 0 | AF90: 40 | AG90: 211 | AH90: =AF90*$AG90 -> 8440 | AJ90: =AI90*$E90 -> 0 | AL90: =AK90*$E90 -> 0 | AN90: =AM90*$E90 -> 0 | AP90: =AO90*$E90 -> 0 | AR90: =AQ90*$E90 -> 0 | AT90: =AS90*$E90 -> 0 | AV90: =AU90*$E90 -> 0 | AX90: =AW90*$E90 -> 0 | AZ90: =AY90*$E90 -> 0 | BB90: =BA90*$E90 -> 0 | BD90: =BC90*$E90 -> 0 | BF90: =BE90*$E90 -> 0 | BH90: =BG90*$E90 -> 0 | BJ90: =BI90*$E90 -> 0 | BL90: =BK90*$E90 -> 0
B91: =IF(ISBLANK($E91)," ",IF(AND(COUNTA(E$83:$E91)+64>72,COUNTA(E$83:$E91)+64<78),CHAR(COUNTA(E$83:$E91)+65),IF(COUNTA(E$83:$E91)+64>77,CHAR(COUNTA(E$83:$E91)+66),CHAR(COUNTA(E$83:$E91)+64)))) -> H | C91: GC/SESU-PO - Sesuvium portulacastrum - Sea purslane | D91: No | E91: 615 | F91: 7.2 | G91: 4428 | H91: 41 | I91: 615 | J91: =H91*$I91 -> 25215 | L91: =K91*$E91 -> 0 | N91: =M91*$E91 -> 0 | P91: =O91*$E91 -> 0 | Q91: 18 | R91: =Q91*$E91 -> 11070 | T91: =S91*$E91 -> 0 | U91: 9 | V91: 615 | W91: =U91*$V91 -> 5535 | Y91: =X91*$E91 -> 0 | AA91: =Z91*$E91 -> 0 | AC91: =AB91*$E91 -> 0 | AE91: =AD91*$E91 -> 0 | AF91: 13 | AG91: 615 | AH91: =AF91*$AG91 -> 7995 | AJ91: =AI91*$E91 -> 0 | AL91: =AK91*$E91 -> 0 | AN91: =AM91*$E91 -> 0 | AP91: =AO91*$E91 -> 0 | AR91: =AQ91*$E91 -> 0 | AT91: =AS91*$E91 -> 0 | AV91: =AU91*$E91 -> 0 | AX91: =AW91*$E91 -> 0 | AZ91: =AY91*$E91 -> 0 | BB91: =BA91*$E91 -> 0 | BD91: =BC91*$E91 -> 0 | BF91: =BE91*$E91 -> 0 | BH91: =BG91*$E91 -> 0 | BJ91: =BI91*$E91 -> 0 | BL91: =BK91*$E91 -> 0
B92: =IF(ISBLANK($E92)," ",IF(AND(COUNTA(E$83:$E92)+64>72,COUNTA(E$83:$E92)+64<78),CHAR(COUNTA(E$83:$E92)+65),IF(COUNTA(E$83:$E92)+64>77,CHAR(COUNTA(E$83:$E92)+66),CHAR(COUNTA(E$83:$E92)+64)))) | C92: Shrubs | H92: =D92*G92 -> 0
B93: =IF(ISBLANK($E93)," ",IF(AND(COUNTA(E$83:$E93)+64>72,COUNTA(E$83:$E93)+64<78),CHAR(COUNTA(E$83:$E93)+65),IF(COUNTA(E$83:$E93)+64>77,CHAR(COUNTA(E$83:$E93)+66),CHAR(COUNTA(E$83:$E93)+64)))) -> J | C93: SH/CYPE-AL - Cyperus alternifolius - mbrella plant. | D93: No | E93: 200 | F93: 36 | G93: 7200 | H93: 41 | I93: 200 | J93: =H93*$I93 -> 8200 | L93: =K93*$E93 -> 0 | N93: =M93*$E93 -> 0 | P93: =O93*$E93 -> 0 | Q93: 74 | R93: =Q93*$E93 -> 14800 | T93: =S93*$E93 -> 0 | U93: 45 | V93: 200 | W93: =U93*$V93 -> 9000 | Y93: =X93*$E93 -> 0 | AA93: =Z93*$E93 -> 0 | AC93: =AB93*$E93 -> 0 | AE93: =AD93*$E93 -> 0 | AF93: 60 | AG93: 200 | AH93: =AF93*$AG93 -> 12000 | AJ93: =AI93*$E93 -> 0 | AL93: =AK93*$E93 -> 0 | AN93: =AM93*$E93 -> 0 | AP93: =AO93*$E93 -> 0 | AR93: =AQ93*$E93 -> 0 | AT93: =AS93*$E93 -> 0 | AV93: =AU93*$E93 -> 0 | AX93: =AW93*$E93 -> 0 | AZ93: =AY93*$E93 -> 0 | BB93: =BA93*$E93 -> 0 | BD93: =BC93*$E93 -> 0 | BF93: =BE93*$E93 -> 0 | BH93: =BG93*$E93 -> 0 | BJ93: =BI93*$E93 -> 0 | BL93: =BK93*$E93 -> 0
B94: =IF(ISBLANK($E94)," ",IF(AND(COUNTA(E$83:$E94)+64>72,COUNTA(E$83:$E94)+64<78),CHAR(COUNTA(E$83:$E94)+65),IF(COUNTA(E$83:$E94)+64>77,CHAR(COUNTA(E$83:$E94)+66),CHAR(COUNTA(E$83:$E94)+64)))) -> K | C94: SH/HIBI-RE - Hibuscus tiliaceus rubra - Sea Hibuscus. | D94: No | E94: 31 | F94: 57.6 | G94: 1785.6 | H94: 68 | I94: 31 | J94: =H94*$I94 -> 2108 | L94: =K94*$E94 -> 0 | N94: =M94*$E94 -> 0 | P94: =O94*$E94 -> 0 | Q94: 81 | R94: =Q94*$E94 -> 2511 | T94: =S94*$E94 -> 0 | U94: 72 | V94: 31 | W94: =U94*$V94 -> 2232 | Y94: =X94*$E94 -> 0 | AA94: =Z94*$E94 -> 0 | AC94: =AB94*$E94 -> 0 | AE94: =AD94*$E94 -> 0 | AF94: 60 | AG94: 31 | AH94: =AF94*$AG94 -> 1860 | AJ94: =AI94*$E94 -> 0 | AL94: =AK94*$E94 -> 0 | AN94: =AM94*$E94 -> 0 | AP94: =AO94*$E94 -> 0 | AR94: =AQ94*$E94 -> 0 | AT94: =AS94*$E94 -> 0 | AV94: =AU94*$E94 -> 0 | AX94: =AW94*$E94 -> 0 | AZ94: =AY94*$E94 -> 0 | BB94: =BA94*$E94 -> 0 | BD94: =BC94*$E94 -> 0 | BF94: =BE94*$E94 -> 0 | BH94: =BG94*$E94 -> 0 | BJ94: =BI94*$E94 -> 0 | BL94: =BK94*$E94 -> 0
B95: =IF(ISBLANK($E95)," ",IF(AND(COUNTA(E$83:$E95)+64>72,COUNTA(E$83:$E95)+64<78),CHAR(COUNTA(E$83:$E95)+65),IF(COUNTA(E$83:$E95)+64>77,CHAR(COUNTA(E$83:$E95)+66),CHAR(COUNTA(E$83:$E95)+64)))) | C95: Climber | H95: =D95*G95 -> 0
B96: =IF(ISBLANK($E96)," ",IF(AND(COUNTA(E$83:$E96)+64>72,COUNTA(E$83:$E96)+64<78),CHAR(COUNTA(E$83:$E96)+65),IF(COUNTA(E$83:$E96)+64>77,CHAR(COUNTA(E$83:$E96)+66),CHAR(COUNTA(E$83:$E96)+64)))) -> L | C96: CL/ANTI-LE - Antigonon leptopus | D96: No | E96: 113 | F96: 53.1 | G96: 4035.6 | H96: 74 | I96: 113 | J96: =H96*$I96 -> 8362 | L96: =K96*$E96 -> 0 | N96: =M96*$E96 -> 0 | P96: =O96*$E96 -> 0 | Q96: 124 | R96: =Q96*$E96 -> 14012 | T96: =S96*$E96 -> 0 | U96: 76 | V96: 86 | W96: =U96*$V96 -> 6536 | Y96: =X96*$E96 -> 0 | AA96: =Z96*$E96 -> 0 | AC96: =AB96*$E96 -> 0 | AE96: =AD96*$E96 -> 0 | AF96: 52 | AG96: 113 | AH96: =AF96*$AG96 -> 5876 | AJ96: =AI96*$E96 -> 0 | AL96: =AK96*$E96 -> 0 | AN96: =AM96*$E96 -> 0 | AP96: =AO96*$E96 -> 0 | AR96: =AQ96*$E96 -> 0 | AT96: =AS96*$E96 -> 0 | AV96: =AU96*$E96 -> 0 | AX96: =AW96*$E96 -> 0 | AZ96: =AY96*$E96 -> 0 | BB96: =BA96*$E96 -> 0 | BD96: =BC96*$E96 -> 0 | BF96: =BE96*$E96 -> 0 | BH96: =BG96*$E96 -> 0 | BJ96: =BI96*$E96 -> 0 | BL96: =BK96*$E96 -> 0
B97: =IF(ISBLANK($E97)," ",IF(AND(COUNTA(E$83:$E97)+64>72,COUNTA(E$83:$E97)+64<78),CHAR(COUNTA(E$83:$E97)+65),IF(COUNTA(E$83:$E97)+64>77,CHAR(COUNTA(E$83:$E97)+66),CHAR(COUNTA(E$83:$E97)+64)))) -> M | C97: PA - Planting Area | D97: m2 | E97: 303.2 | F97: 118.8 | G97: 51440.4 | H97: 142 | I97: 303 | J97: =H97*$I97 -> 43026 | L97: =K97*$E97 -> 0 | N97: =M97*$E97 -> 0 | P97: =O97*$E97 -> 0 | Q97: 124 | R97: =Q97*$E97 -> 37596.8 | T97: =S97*$E97 -> 0 | U97: 149 | V97: 433 | W97: =U97*$V97 -> 64517 | Y97: =X97*$E97 -> 0 | AA97: =Z97*$E97 -> 0 | AC97: =AB97*$E97 -> 0 | AE97: =AD97*$E97 -> 0 | AG97: 303.2 | AH97: =AF97*$AG97 -> 0 | AJ97: =AI97*$E97 -> 0 | AL97: =AK97*$E97 -> 0 | AN97: =AM97*$E97 -> 0 | AP97: =AO97*$E97 -> 0 | AR97: =AQ97*$E97 -> 0 | AT97: =AS97*$E97 -> 0 | AV97: =AU97*$E97 -> 0 | AX97: =AW97*$E97 -> 0 | AZ97: =AY97*$E97 -> 0 | BB97: =BA97*$E97 -> 0 | BD97: =BC97*$E97 -> 0 | BF97: =BE97*$E97 -> 0 | BH97: =BG97*$E97 -> 0 | BJ97: =BI97*$E97 -> 0 | BL97: =BK97*$E97 -> 0
C98: Outdoor Furniture and Plant pots | BK98: unbonded
C99: Kid's play area
B100: =IF(ISBLANK($E100)," ",IF(AND(COUNTA(E$97:$E100)+64>72,COUNTA(E$97:$E100)+64<78),CHAR(COUNTA(E$97:$E100)+65),IF(COUNTA(E$97:$E100)+64>77,CHAR(COUNTA(E$97:$E100)+66),CHAR(COUNTA(E$97:$E100)+64)))) -> B | C100: PP01 GRC Planter pot | D100: No | E100: 1 | F100: 43369.2 | G100: 43369.2 | I100: 1 | J100: =H100*$I100 -> 0 | L100: =K100*$E100 -> 0 | N100: =M100*$E100 -> 0 | P100: =O100*$E100 -> 0 | R100: =Q100*$E100 -> 0 | T100: =S100*$E100 -> 0 | U100: 54701 | V100: 1 | W100: =U100*$V100 -> 54701 | Y100: =X100*$E100 -> 0 | AA100: =Z100*$E100 -> 0 | AC100: =AB100*$E100 -> 0 | AE100: =AD100*$E100 -> 0 | AF100: 3334 | AG100: 1 | AH100: =AF100*$AG100 -> 3334 | AJ100: =AI100*$E100 -> 0 | AL100: =AK100*$E100 -> 0 | AN100: =AM100*$E100 -> 0 | AP100: =AO100*$E100 -> 0 | AR100: =AQ100*$E100 -> 0 | AT100: =AS100*$E100 -> 0 | AV100: =AU100*$E100 -> 0 | AX100: =AW100*$E100 -> 0 | AZ100: =AY100*$E100 -> 0 | BB100: =BA100*$E100 -> 0 | BD100: =BC100*$E100 -> 0 | BF100: =BE100*$E100 -> 0 | BH100: =BG100*$E100 -> 0 | BJ100: =BI100*$E100 -> 0 | BL100: =BK100*$E100 -> 0
B101: =IF(ISBLANK($E101)," ",IF(AND(COUNTA(E$97:$E101)+64>72,COUNTA(E$97:$E101)+64<78),CHAR(COUNTA(E$97:$E101)+65),IF(COUNTA(E$97:$E101)+64>77,CHAR(COUNTA(E$97:$E101)+66),CHAR(COUNTA(E$97:$E101)+64)))) -> C | C101: PP02 GRC Planter pot | D101: No | E101: 8 | F101: 3787.2 | G101: 37872 | I101: 8 | J101: =H101*$I101 -> 0 | L101: =K101*$E101 -> 0 | N101: =M101*$E101 -> 0 | P101: =O101*$E101 -> 0 | R101: =Q101*$E101 -> 0 | T101: =S101*$E101 -> 0 | U101: 4776 | V101: 10 | W101: =U101*$V101 -> 47760 | Y101: =X101*$E101 -> 0 | AA101: =Z101*$E101 -> 0 | AC101: =AB101*$E101 -> 0 | AE101: =AD101*$E101 -> 0 | AF101: 4000 | AG101: 8 | AH101: =AF101*$AG101 -> 32000 | AJ101: =AI101*$E101 -> 0 | AL101: =AK101*$E101 -> 0 | AN101: =AM101*$E101 -> 0 | AP101: =AO101*$E101 -> 0 | AR101: =AQ101*$E101 -> 0 | AT101: =AS101*$E101 -> 0 | AV101: =AU101*$E101 -> 0 | AX101: =AW101*$E101 -> 0 | AZ101: =AY101*$E101 -> 0 | BB101: =BA101*$E101 -> 0 | BD101: =BC101*$E101 -> 0 | BF101: =BE101*$E101 -> 0 | BH101: =BG101*$E101 -> 0 | BJ101: =BI101*$E101 -> 0 | BL101: =BK101*$E101 -> 0
B102: =IF(ISBLANK($E102)," ",IF(AND(COUNTA(E$97:$E102)+64>72,COUNTA(E$97:$E102)+64<78),CHAR(COUNTA(E$97:$E102)+65),IF(COUNTA(E$97:$E102)+64>77,CHAR(COUNTA(E$97:$E102)+66),CHAR(COUNTA(E$97:$E102)+64)))) -> D | C102: PP02A GRC Planter pot | D102: No | E102: 19 | F102: 3787.2 | G102: 71956.8 | I102: 19 | J102: =H102*$I102 -> 0 | L102: =K102*$E102 -> 0 | N102: =M102*$E102 -> 0 | P102: =O102*$E102 -> 0 | R102: =Q102*$E102 -> 0 | T102: =S102*$E102 -> 0 | U102: 4776 | V102: 19 | W102: =U102*$V102 -> 90744 | Y102: =X102*$E102 -> 0 | AA102: =Z102*$E102 -> 0 | AC102: =AB102*$E102 -> 0 | AE102: =AD102*$E102 -> 0 | AF102: 4000 | AG102: 19 | AH102: =AF102*$AG102 -> 76000 | AJ102: =AI102*$E102 -> 0 | AL102: =AK102*$E102 -> 0 | AN102: =AM102*$E102 -> 0 | AP102: =AO102*$E102 -> 0 | AR102: =AQ102*$E102 -> 0 | AT102: =AS102*$E102 -> 0 | AV102: =AU102*$E102 -> 0 | AX102: =AW102*$E102 -> 0 | AZ102: =AY102*$E102 -> 0 | BB102: =BA102*$E102 -> 0 | BD102: =BC102*$E102 -> 0 | BF102: =BE102*$E102 -> 0 | BH102: =BG102*$E102 -> 0 | BJ102: =BI102*$E102 -> 0 | BL102: =BK102*$E102 -> 0
B103: =IF(ISBLANK($E103)," ",IF(AND(COUNTA(E$97:$E103)+64>72,COUNTA(E$97:$E103)+64<78),CHAR(COUNTA(E$97:$E103)+65),IF(COUNTA(E$97:$E103)+64>77,CHAR(COUNTA(E$97:$E103)+66),CHAR(COUNTA(E$97:$E103)+64)))) -> E | C103: PP03 GRC Planter pot | D103: No | E103: 1 | F103: 4829.4 | G103: 43464.6 | I103: 1 | J103: =H103*$I103 -> 0 | L103: =K103*$E103 -> 0 | N103: =M103*$E103 -> 0 | P103: =O103*$E103 -> 0 | R103: =Q103*$E103 -> 0 | T103: =S103*$E103 -> 0 | U103: 6091 | V103: 9 | W103: =U103*$V103 -> 54819 | Y103: =X103*$E103 -> 0 | AA103: =Z103*$E103 -> 0 | AC103: =AB103*$E103 -> 0 | AE103: =AD103*$E103 -> 0 | AF103: 2667 | AG103: 1 | AH103: =AF103*$AG103 -> 2667 | AJ103: =AI103*$E103 -> 0 | AL103: =AK103*$E103 -> 0 | AN103: =AM103*$E103 -> 0 | AP103: =AO103*$E103 -> 0 | AR103: =AQ103*$E103 -> 0 | AT103: =AS103*$E103 -> 0 | AV103: =AU103*$E103 -> 0 | AX103: =AW103*$E103 -> 0 | AZ103: =AY103*$E103 -> 0 | BB103: =BA103*$E103 -> 0 | BD103: =BC103*$E103 -> 0 | BF103: =BE103*$E103 -> 0 | BH103: =BG103*$E103 -> 0 | BJ103: =BI103*$E103 -> 0 | BL103: =BK103*$E103 -> 0
...
